{
  "subject": "Lý Thuyết Mạng Máy Tính",
  "chapters": [
    {
      "id": "chuong_1",
      "title": "CHƯƠNG 1: TỔNG QUAN VỀ MẠNG MÁY TÍNH VÀ INTERNET",
      "content": "# CHƯƠNG 1: TỔNG QUAN VỀ MẠNG MÁY TÍNH VÀ INTERNET\n\n## 1.1 Khái quát về Internet và Mạng máy tính\n\n### 1.1.1 Internet là gì?\nInternet là mạng lưới khổng lồ kết nối hàng tỷ thiết bị điện toán trên toàn cầu. Các thiết bị này không chỉ giới hạn ở máy tính để bàn (desktop) hay máy tính xách tay (laptop), mà còn bao gồm điện thoại thông minh (smartphone), tivi thông minh, máy chủ web (web server), các cảm biến IoT (Internet of Things) và cả ô tô tự lái. Trong thuật ngữ chuyên ngành mạng, tất cả các thiết bị kết nối vào mạng này được gọi chung là **host** (máy chủ/máy trạm) hoặc **end system** (hệ thống đầu cuối).\n\nCác end system kết nối với nhau thông qua mạng lưới các **communication link** (đường truyền truyền thông) và **packet switch** (bộ chuyển mạch gói).\n- **Communication link**: Được làm từ nhiều loại phương tiện vật lý khác nhau, chẳng hạn như cáp đồng trục (coaxial cable), cáp đồng bện (copper wire), cáp quang (optical fiber) và phổ vô tuyến (radio spectrum). Mỗi loại đường truyền có một tốc độ truyền tải dữ liệu nhất định, được đo bằng bit/giây (bits per second - bps), gọi là **transmission rate** hoặc **bandwidth** (băng thông).\n- **Packet switch**: Khi một hệ thống đầu cuối gửi dữ liệu đến một hệ thống đầu cuối khác, thiết bị gửi phân chia dữ liệu thành các đoạn nhỏ và thêm header (phần tiêu đề) vào mỗi đoạn. Các gói dữ liệu này được gọi là **packet** (gói tin). Packet switch nhận các gói tin trên một trong các đường truyền đầu vào và chuyển tiếp chúng ra một trong các đường truyền đầu ra. Hai loại packet switch nổi bật nhất trong mạng Internet ngày nay là **router** (bộ định tuyến) và **link-layer switch** (bộ chuyển mạch tầng liên kết). Switch thường được sử dụng trong các mạng truy cập (access network), trong khi router thường được sử dụng ở lõi mạng (network core).\n\nĐường dẫn mà một gói tin đi từ hệ thống nguồn đến hệ thống đích thông qua chuỗi các đường truyền và packet switch được gọi là **route** (tuyến đường) hoặc **path** (đường đi).\n\nInternet, về cơ bản, là mạng lưới của các mạng (network of networks). Các end system truy cập vào Internet thông qua các **Internet Service Provider (ISP)** (Nhà cung cấp dịch vụ Internet). Các ISP cung cấp quyền truy cập mạng lưới cho các hộ gia đình (ví dụ: VNPT, Viettel, FPT), cung cấp truy cập mạng di động, và truy cập mạng cho doanh nghiệp/trường học. Bản thân các ISP cũng phải kết nối với nhau để cho phép người dùng ở bất kỳ ISP nào cũng có thể tương tác với người dùng ở ISP khác. Do đó, mạng lưới ISP là một cấu trúc phân cấp, bao gồm các ISP cấp dưới (như ISP khu vực) và các ISP cấp trên (ISP quốc gia/quốc tế hay còn gọi là Tier-1 ISP).\n\n### 1.1.2 Giao thức (Protocol) là gì?\nTrong mạng máy tính, các end system, packet switch và mọi mảnh ghép của Internet đều hoạt động dưới sự điều khiển của các **protocol** (giao thức). Giao thức kiểm soát việc gửi và nhận thông tin bên trong mạng lưới.\n\nMột định nghĩa dễ hiểu về giao thức trong thế giới thực là các quy tắc ứng xử của con người. Ví dụ, khi bạn hỏi giờ một người, bạn tuân theo quy tắc: gửi lời chào, sau đó hỏi giờ. Người kia sẽ đáp lại bằng câu trả lời thời gian hiện tại. Tương tự, giao thức mạng định nghĩa định dạng (format), thứ tự (order) của các thông điệp được gửi và nhận giữa các thực thể trên mạng, cũng như các hành động được thực hiện (actions taken) khi truyền/nhận các thông điệp đó.\n\nMột số giao thức nổi tiếng như: TCP (Transmission Control Protocol), IP (Internet Protocol), HTTP (HyperText Transfer Protocol), Ethernet, Wi-Fi (802.11). Trong đó, IP là giao thức đóng vai trò vô cùng quan trọng vì nó xác định định dạng của các gói tin được định tuyến qua mạng Internet từ nguồn tới đích. Kết hợp lại, TCP và IP là các giao thức cốt lõi nhất của Internet, dẫn đến việc kiến trúc của Internet được gọi chung là kiến trúc TCP/IP.\n\nĐể đảm bảo tính tương thích và khả năng làm việc cùng nhau của mọi thiết bị và phần mềm từ các nhà sản xuất khác nhau, các giao thức được chuẩn hóa bởi tổ chức IETF (Internet Engineering Task Force). Các tài liệu chuẩn của IETF được gọi là RFC (Request for Comments).\n\n---\n\n## 1.2 Rìa mạng (The Network Edge)\n\nHệ thống mạng được phân chia thành rìa mạng và lõi mạng. Rìa mạng bao gồm các thiết bị đầu cuối (end systems / hosts). Các host thường được chia thành 2 loại: **client** (máy khách) và **server** (máy chủ).\n- Client: Là những thiết bị như PC, điện thoại di động yêu cầu và tiếp nhận dịch vụ từ các thiết bị khác.\n- Server: Thường là những máy tính mạnh mẽ lưu trữ và phân phối tài nguyên (Web page, Video, Email) phục vụ yêu cầu từ client. Hầu hết các server ngày nay nằm trong các data center (trung tâm dữ liệu) khổng lồ của Google, Amazon, Microsoft,...\n\n### 1.2.1 Mạng truy cập (Access Networks)\nMạng truy cập là mạng vật lý kết nối end system vào edge router (bộ định tuyến biên) – router đầu tiên trên con đường từ hệ thống đầu cuối nguồn đi đến hệ thống đầu cuối đích.\n\n**1. Mạng truy cập hộ gia đình (Home Access):**\n- **DSL (Digital Subscriber Line):** Truy cập băng thông rộng qua đường dây điện thoại bằng đồng. ISP cấp dịch vụ Internet cũng chính là công ty cung cấp dịch vụ điện thoại nội hạt. DSL sử dụng kỹ thuật ghép kênh phân chia tần số (Frequency Division Multiplexing - FDM) để truyền đồng thời dữ liệu mạng, âm thanh điện thoại. DSL có đặc điểm bất đối xứng (asymmetric), tốc độ tải xuống (download) thường cao hơn tốc độ tải lên (upload).\n- **Cable (Mạng cáp):** Tận dụng hệ thống truyền hình cáp. Thay vì dây đồng đôi xoắn, cáp đồng trục và sợi quang được sử dụng. Đặc trưng của cable là chia sẻ môi trường truyền thông (shared medium) – tất cả các hộ gia đình dùng chung một đường cáp sẽ cùng chia sẻ băng thông.\n- **FTTH (Fiber to the Home):** Kéo trực tiếp sợi cáp quang từ văn phòng trung tâm của ISP đến nhà người dùng. Cung cấp tốc độ cực cao. Kỹ thuật chia sẻ tín hiệu quang phổ biến là PON (Passive Optical Network) và AON (Active Optical Network). Hiện nay mạng truy cập ở Việt Nam hầu hết sử dụng công nghệ FTTH.\n\n**2. Mạng truy cập doanh nghiệp (Enterprise Access):**\nDoanh nghiệp và trường học thường sử dụng Local Area Network (LAN) để kết nối máy tính của người dùng tới edge router. Công nghệ LAN phổ biến nhất là Ethernet, hoạt động dựa trên môi trường dây đồng bện hoặc cáp quang với tốc độ 100 Mbps, 1 Gbps, 10 Gbps và thậm chí cao hơn.\n\n**3. Mạng truy cập không dây (Wireless Access Networks):**\n- **Wireless LAN (WLAN):** Mạng không dây cục bộ hoạt động trong một phạm vi nhỏ (như nhà riêng, văn phòng, quán cà phê). Phổ biến nhất là Wi-Fi (chuẩn IEEE 802.11).\n- **Wide-area wireless access networks:** Mạng di động diện rộng được cung cấp bởi các nhà mạng viễn thông (telcos) và trải dài trên hàng chục kilomet (ví dụ 3G, 4G LTE, 5G).\n\n### 1.2.2 Phương tiện vật lý (Physical Media)\nBit dữ liệu được truyền từ nguồn đến đích bằng cách lan truyền qua các phương tiện vật lý. Các phương tiện này được chia làm hai loại:\n- **Guided media (Phương tiện hữu tuyến/dẫn hướng):** Sóng tín hiệu truyền dọc theo một môi trường vật lý rắn, ví dụ như dây đồng bện (twisted-pair copper wire), cáp đồng trục (coaxial cable), sợi cáp quang (fiber optics).\n  - Cáp quang: Mang ánh sáng xung, mỗi xung là một bit. Cáp quang có khả năng miễn nhiễm với nhiễu điện từ, tín hiệu ít bị suy hao với cự ly xa, mang lại tốc độ có thể lên tới Tbps.\n- **Unguided media (Phương tiện vô tuyến/không dẫn hướng):** Sóng điện từ truyền lan trong không gian tự do. Ví dụ: Radio mặt đất, Radio vệ tinh (Geostationary satellites và Low-earth orbiting - LEO satellites như Starlink). Môi trường vô tuyến gặp phải các thách thức về sự phản xạ, che khuất vật lý, và nhiễu sóng (interference).\n\n---\n\n## 1.3 Lõi mạng (The Network Core)\n\nLõi mạng là mảng lưới các bộ định tuyến (router) và liên kết (link) dùng để kết nối những rìa mạng của Internet lại với nhau. Câu hỏi mấu chốt là làm sao dữ liệu đi xuyên qua hệ thống mạng lõi đồ sộ này? Có hai phương pháp chuyển mạch cốt lõi là **Packet Switching** (Chuyển mạch gói) và **Circuit Switching** (Chuyển mạch kênh).\n\n### 1.3.1 Packet Switching (Chuyển mạch gói)\nTrong các ứng dụng mạng, end systems trao đổi các bản tin (message). Để gửi một bản tin, thiết bị nguồn cắt bản tin đó ra thành các khối nhỏ hơn gọi là packet (gói tin). Giữa điểm nguồn và đích, gói tin được đi qua nhiều liên kết truyền thông (communication link) và packet switch (thường là router). Gói tin sẽ được truyền với tốc độ tối đa của liên kết vật lý (link transmission rate).\n\n**Store-and-Forward Transmission (Lưu và chuyển tiếp):**\nHầu hết các packet switch đều sử dụng nguyên lý truyền lưu-và-chuyển-tiếp. Tức là bộ chuyển mạch phải nhận ĐẦY ĐỦ toàn bộ gói tin từ đường dẫn đầu vào trước khi nó có thể bắt đầu đẩy byte đầu tiên của gói tin đó ra đường dẫn đầu ra. Điều này gây ra một độ trễ gọi là Store-and-Forward delay. Chẳng hạn, gửi gói tin có kích thước L (bits) qua đường truyền tốc độ R (bps) thì độ trễ của nguyên lý lưu-chuyển-tiếp trên 1 link là L/R giây.\n\n**Queuing Delay và Packet Loss (Độ trễ hàng đợi và mất gói tin):**\nMỗi packet switch có nhiều liên kết, mỗi liên kết có một bộ đệm đầu ra (output buffer) hoặc hàng đợi (queue). Nếu một gói tin đi đến và thấy đường truyền đầu ra đang bận rộn vì đang phải gửi các gói tin khác, nó sẽ phải chờ trong hàng đợi. Độ trễ chờ đợi này được gọi là queuing delay. Nếu hàng đợi đã đầy mà một gói tin mới lại đến, bộ đệm không còn chỗ chứa, gói tin đó sẽ bị loại bỏ (drop), hiện tượng này gọi là packet loss (mất gói tin).\n\n**Forwarding và Routing (Chuyển tiếp và Định tuyến):**\nTại router, mỗi gói tin đều mang địa chỉ đích đến (destination IP address). Router sở hữu một **forwarding table** (bảng chuyển tiếp) giúp ánh xạ địa chỉ đích (hoặc dải địa chỉ) đến đường dẫn đầu ra tương ứng. Khi gói tin tới, router dựa vào địa chỉ đích để tra bảng và đẩy gói tin vào giao diện đầu ra thích hợp.\n- **Routing protocols**: Là những giao thức tự động cấu hình các bảng chuyển tiếp trong router (như OSPF, BGP) dựa trên giải thuật để tìm ra con đường ngắn nhất và tối ưu nhất từ nguồn tới đích.\n\n### 1.3.2 Circuit Switching (Chuyển mạch kênh)\nTrái với chuyển mạch gói, trong chuyển mạch kênh, tài nguyên (như băng thông) trên toàn bộ tuyến đường từ nguồn đến đích được DÀNH RIÊNG (reserved) trước khi diễn ra việc truyền tải dữ liệu, và tồn tại trong suốt phiên giao tiếp (session). Mạng điện thoại truyền thống là ví dụ điển hình của Circuit Switching.\n\nCác kỹ thuật để chia sẻ băng thông trong chuyển mạch kênh bao gồm:\n- **FDM (Frequency-Division Multiplexing):** Băng thông của liên kết chia thành các dải tần số nhỏ hơn (frequency bands), mỗi kết nối (kênh) dùng riêng một dải tần số ổn định suốt thời gian kết nối.\n- **TDM (Time-Division Multiplexing):** Thời gian truyền được chia thành các khung hình (frames) có kích thước cố định, trong mỗi frame lại chia ra các khe thời gian (slots). Mỗi kết nối được cấp phép sử dụng 1 khe thời gian trong 1 frame để truyền. Do đó tốc độ sẽ bằng tốc độ đường link chia cho số khe thời gian trong khung.\n\n**Packet Switching vs Circuit Switching:**\nPacket switching không yêu cầu thiết lập mạch riêng ảo. Nó linh hoạt hơn, sử dụng tài nguyên hiệu quả hơn (statistical multiplexing) và phục vụ được nhiều người dùng hơn. Tuy nhiên, chuyển mạch gói không thể đảm bảo chắc chắn về độ trễ, tốc độ, nên không phù hợp hoàn toàn với các yêu cầu thời gian thực khắt khe. Ngược lại, circuit switching đảm bảo được tài nguyên truyền tải, nhưng làm lãng phí rất nhiều tài nguyên (silent periods - người dùng không truyền thì tài nguyên cũng không ai được dùng). Internet ngày nay dựa hoàn toàn trên nền tảng chuyển mạch gói (Packet Switching).\n\n---\n\n## 1.4 Độ trễ (Delay), Mất gói (Loss) và Băng thông (Throughput) trong mạng Packet-Switched\n\nHiểu về hiệu năng mạng đồng nghĩa với việc hiểu về 3 yếu tố quan trọng nhất: Delay, Loss và Throughput.\n\n### 1.4.1 Bốn nguồn gốc của độ trễ (Delay)\nKhi một gói tin di chuyển từ một node sang node tiếp theo dọc con đường, gói tin sẽ gặp phải nhiều loại độ trễ khác nhau:\n1. **Nodal Processing Delay (Trễ xử lý tại nút):** Thời gian cần thiết để router kiểm tra header của gói tin và quyết định cổng đầu ra nào cần chuyển tới. Nó cũng bao gồm thời gian kiểm tra lỗi bit ở cấp độ link-layer. Trễ xử lý thường rất nhỏ (vài microsecond).\n2. **Queuing Delay (Trễ hàng đợi):** Thời gian gói tin phải chờ ở hàng đợi đầu ra trước khi đến lượt được phát lên đường truyền. Độ trễ này phụ thuộc vào tình trạng tắc nghẽn của mạng, có thể dao động từ 0 đến vài milisecond.\n3. **Transmission Delay (Trễ truyền đi):** Hay còn gọi là độ trễ đẩy (push delay). Là thời gian để router đẩy toàn bộ L bits của gói tin lên đường liên kết vật lý. Nếu R là transmission rate (bps), thì Trễ truyền đi = L / R. Tốc độ R phụ thuộc vào dung lượng mạng (VD: 10Mbps tới 10Gbps).\n4. **Propagation Delay (Trễ lan truyền):** Thời gian để một bit sau khi lên đường truyền có thể chạy qua môi trường vật lý từ node A sang node B. Phụ thuộc vào khoảng cách (d) giữa 2 node và tốc độ truyền tín hiệu điện từ qua môi trường đó (v, xấp xỉ tốc độ ánh sáng ~ 2x10^8 đến 3x10^8 m/s). Propagation Delay = d / v.\n\n**Phân biệt Transmission Delay và Propagation Delay:**\nTransmission Delay là thời gian router đẩy gói tin vào đường dây (phụ thuộc vào chiều dài gói tin L và băng thông R, không phụ thuộc khoảng cách). Propagation Delay là thời gian tín hiệu bit trôi trong cáp từ node này sang node kia (phụ thuộc khoảng cách d, không phụ thuộc kích cỡ gói tin và tốc độ link R).\n\n*Tổng Nodal Delay = Nodal Processing Delay + Queuing Delay + Transmission Delay + Propagation Delay*\n\n### 1.4.2 Mất gói tin (Packet Loss)\nNếu tỉ lệ các gói tin đến router quá lớn trong một khoảng thời gian dài, hàng đợi (queue) sẽ bị đầy (buffer overflow). Vì khả năng lưu trữ là có hạn, một gói tin đến nơi khi hàng đợi không còn chỗ chứa sẽ bị \"drop\" (bị loại bỏ) và gây ra hiện tượng mất gói tin.\nĐể xử lý, các gói tin bị mất đôi khi có thể được re-transmitted (gửi lại) từ các thiết bị end systems nhờ các giao thức ở tầng trên (như TCP). Tuy nhiên điều này lại làm tăng delay nói chung cho toàn bộ luồng truyền.\n\n### 1.4.3 Thông lượng (Throughput)\nThông lượng là tốc độ truyền dữ liệu THỰC TẾ đang diễn ra trên mạng (số bits / giây) giữa tiến trình gửi và tiến trình nhận.\n- **Instantaneous throughput (Thông lượng tức thời):** Tốc độ truyền ở một khoảng thời gian cực ngắn nào đó.\n- **Average throughput (Thông lượng trung bình):** Tốc độ truyền trên một khoảng thời gian dài hơn (Tổng file size F / Thời gian truyền T).\n- **Nút thắt cổ chai (Bottleneck link):** Giả sử file đi qua 1 link Rc, một link Rs. Nếu Rs < Rc, throughput của kết nối đầu cuối (end-to-end throughput) sẽ bị giới hạn bởi Rs. Liên kết có tốc độ thấp nhất trên path cản trở toàn bộ throughput được gọi là bottleneck link. Trên mạng Internet ngày nay, bottleneck link thường nằm tại các mạng truy cập (Access network).\n\n---\n\n## 1.5 Kiến trúc phân tầng và Mô hình tham chiếu (Protocol Layers and Service Models)\n\nVì mạng máy tính và Internet là một hệ thống cực kỳ phức tạp bao gồm ứng dụng, hệ điều hành, vô vàn các giao thức, thiết bị kết nối. Các nhà thiết kế mạng đã dùng cách **Phân tầng (Layering)** để thiết kế hệ thống. Mỗi tầng giải quyết một vấn đề nhỏ hẹp của quá trình kết nối và cung cấp dịch vụ (service) cho tầng nằm ngay trên nó dựa vào những dịch vụ của tầng nằm dưới.\n\nLợi ích của phân tầng:\n- Cấu trúc hoá công việc phức tạp, cho phép xác định rõ mối quan hệ tương tác giữa các phần tử.\n- Thiết kế theo dạng module, dễ dàng cập nhật và bảo trì. Thay đổi chi tiết thực thi của một tầng không làm ảnh hưởng đến các tầng khác.\n\nCó hai mô hình phân tầng phổ biến: Mô hình OSI và Mô hình TCP/IP.\n\n### 1.5.1 Mô hình Internet (TCP/IP)\nKiến trúc Internet ngày nay dựa trên 5 tầng (layers):\n\n1. **Tầng ứng dụng (Application Layer):**\n   - Đây là nơi các ứng dụng mạng (Network applications) và giao thức ở tầng ứng dụng cư trú.\n   - Các giao thức nổi bật: HTTP (để truyền tải Web), SMTP (truyền email), FTP (truyền file), DNS (phân giải tên miền).\n   - Đơn vị dữ liệu: **Message** (Bản tin).\n2. **Tầng giao vận (Transport Layer):**\n   - Nhiệm vụ chuyển bản tin của Application layer từ một process (tiến trình) của máy này tới một process ở máy khác.\n   - Hai giao thức chính là TCP và UDP. TCP đảm bảo truyền tin tin cậy, không mất gói, đúng thứ tự, và có kiểm soát luồng/tắc nghẽn. UDP truyền tin phi kết nối, không đáng tin cậy nhưng tốc độ nhanh (phù hợp truyền video/âm thanh).\n   - Đơn vị dữ liệu: **Segment** (Đoạn tin).\n3. **Tầng mạng (Network Layer):**\n   - Chịu trách nhiệm chuyển một gói tin của mạng (Datagram) từ một host (máy chủ) này đến một host khác ở đâu đó trên toàn cầu thông qua nhiều router.\n   - Giao thức cốt lõi là giao thức IP (Internet Protocol) định nghĩa cấu trúc của datagram và cách đánh địa chỉ. Cùng với đó là các giao thức định tuyến (Routing protocols) giúp tìm đường đi tốt nhất.\n   - Đơn vị dữ liệu: **Datagram** (Gói tin).\n4. **Tầng liên kết (Link Layer):**\n   - Để đẩy packet từ một node tới node kề cận theo một đường dẫn, network layer giao datagram cho link layer. Link layer chịu trách nhiệm truyền datagram giữa các nút (node) đứng liền kề qua link vật lý.\n   - Các giao thức tiêu biểu: Ethernet, Wi-Fi 802.11, DOCSIS, PPP.\n   - Đơn vị dữ liệu: **Frame** (Khung).\n5. **Tầng vật lý (Physical Layer):**\n   - Chuyển tiếp các bits trong frame từ node này sang node tiếp theo. Giao thức ở tầng này hoàn toàn phụ thuộc vào đặc tính của môi trường truyền vật lý (cáp đồng, cáp quang, sóng vô tuyến).\n\n### 1.5.2 Mô hình tham chiếu OSI (OSI Model)\nVào cuối thập niên 1970, Tổ chức Tiêu chuẩn Quốc tế (ISO) đề xuất mô hình 7 tầng gọi là OSI (Open Systems Interconnection). Dù hiện nay TCP/IP đã là tiêu chuẩn thực tế của Internet, mô hình OSI vẫn có ý nghĩa hàn lâm rất lớn trong đào tạo. 7 tầng của OSI gồm có:\n\n1. **Physical Layer**: Truyền bit trên môi trường vật lý.\n2. **Data Link Layer**: Khung hóa, địa chỉ vật lý (MAC), kiểm soát lỗi node-to-node.\n3. **Network Layer**: Định tuyến và địa chỉ logic (IP).\n4. **Transport Layer**: Truyền tải tin cậy end-to-end, gộp kênh.\n5. **Session Layer (Tầng phiên):** Cung cấp các công cụ cấu trúc dữ liệu, đồng bộ hóa, thiết lập, quản lý và kết thúc các phiên làm việc giữa các ứng dụng. (Trong TCP/IP, vai trò này được đẩy lên cho tầng Application quyết định).\n6. **Presentation Layer (Tầng trình diễn):** Cho phép các ứng dụng diễn giải ý nghĩa của dữ liệu được truyền, giải quyết các khác biệt về định dạng dữ liệu như mã hóa dữ liệu (encryption), nén dữ liệu (compression). (Trong TCP/IP, vai trò này cũng thuộc tầng Application).\n7. **Application Layer**: Giao diện với người dùng/ứng dụng.\n\n### 1.5.3 Quá trình Đóng gói (Encapsulation)\nTại host gửi, một *Message* từ application layer được gửi xuống transport layer. Transport layer đính kèm thông tin header của nó (như port number) vào message tạo thành một *Segment*. Sau đó transport layer gửi segment xuống network layer.\nNetwork layer thêm header của nó (như địa chỉ IP nguồn/đích) tạo thành *Datagram* rồi gửi xuống link layer. Link layer lại thêm header (như MAC address) để tạo thành *Frame* trước khi được chuyển đổi thành chuỗi bit truyền qua Physical layer. Quá trình bọc các lớp header này vào payload gọi là **Đóng gói (Encapsulation)**. Tại host nhận, quá trình ngược lại gọi là Giải đóng gói (Decapsulation) được thực hiện. Các packet switch, như router chỉ giải mã tới tầng Network, trong khi link-layer switch chỉ giải mã tới tầng Link.\n\n---\n\n## 1.6 An ninh Mạng cơ bản (Network Security)\n\nMạng Internet ban đầu được thiết kế với tư duy về một nhóm người dùng tin cậy với nhau. Thật không may, Internet ngày nay có vô vàn các nguy cơ đe dọa bảo mật. Những kẻ tấn công (hackers, botnet) luôn rình rập và có thể tấn công từ bất kỳ đâu.\n\n### 1.6.1 Mã độc (Malware)\nHacker có thể đính kèm mã độc vào các thiết bị. Mã độc có thể xóa tập tin, thu thập mật khẩu, theo dõi bàn phím (spyware). Mã độc có thể xâm nhập bằng cách lừa người dùng tải về file độc hại. Khi đã xâm nhập vào thiết bị, malware có thể lây lan cho các host khác thành mạng lưới **botnet** dùng cho các cuộc tấn công DDoS hay phát tán spam email. Các loại malware lây lan nhanh được gọi là **virus** (cần sự tương tác của con người để lây nhiễm, VD mở file đính kèm email) hoặc **worm** (có thể tự lây nhiễm từ máy này sang máy khác qua lỗ hổng mà không cần người thao tác).\n\n### 1.6.2 Tấn công Từ chối dịch vụ (Denial of Service - DoS)\nTấn công DoS có thể làm sập một hệ thống mạng, một server hoặc một ứng dụng khiến dịch vụ không thể phục vụ người dùng hợp pháp. Tấn công DoS gồm ba loại hình chính:\n- **Vulnerability attack:** Khai thác lỗi phần mềm/hệ điều hành bằng vài message dị biệt làm sập hệ thống.\n- **Bandwidth flooding:** Hacker gửi lượng lớn gói tin liên tục nhắm vào đường truyền để bóp chết băng thông (ví dụ UDP flooding).\n- **Connection flooding:** Hacker thiết lập hàng ngàn kết nối TCP một nửa (half-open) làm máy chủ hết cạn kiệt tài nguyên duy trì các kết nối ma này.\n\nMột biến thể rất khó chống đỡ là **DDoS (Distributed DoS)**, nơi kẻ tấn công điều khiển hàng trăm ngàn máy tính bị nhiễm malware (botnet) cùng tập trung gửi traffic rác về mục tiêu duy nhất cùng một lúc.\n\n### 1.6.3 Sniffing (Nghe lén) và Spoofing (Giả mạo)\n- **Packet Sniffing (Nghe lén gói tin):** Kẻ tấn công đặt thiết bị ở gần và trong cùng một môi trường mạng LAN, có khả năng lấy cắp được mọi bản sao của gói tin đang truyền. Những dữ liệu nhạy cảm nếu không được mã hóa (ví dụ dùng HTTP thay vì HTTPS) sẽ bị lộ hoàn toàn mật khẩu.\n- **IP Spoofing (Giả mạo IP):** Hacker thay đổi Header của IP, tạo ra một gói tin có địa chỉ IP nguồn (Source IP) giả mạo, giả vờ là mình là một người dùng đáng tin cậy hợp pháp trong mạng để xâm nhập. Các bộ lọc firewall tiên tiến mới có thể ngăn cản được phần nào kiểu giả mạo IP bằng giải pháp end-point authentication (chứng thực người dùng cuối ở mức chữ ký số).\n\n---\n\n## TÓM TẮT NHỮNG ĐIỂM CHÍNH (KEY TAKEAWAYS)\n- Internet là một mạng của các mạng kết nối thiết bị đầu cuối với nhau thông qua mạng ISP, router, link.\n- Giao thức định nghĩa các quy tắc giao tiếp. Cốt lõi của Internet là TCP/IP.\n- Rìa mạng gồm các Host (End system) chia làm Client, Server.\n- Lõi mạng sử dụng Packet switching (chuyển mạch gói), tối ưu và chia sẻ tài nguyên động nhưng không bảo đảm chất lượng thời gian thực thay vì Circuit switching (chuyển mạch kênh).\n- Router thực hiện Forwarding (đẩy gói tin ở mức địa phương) và Routing (tìm đường liên kết mức toàn cục).\n- 4 loại độ trễ mạng: Nodal processing, Queuing, Transmission (L/R) và Propagation (d/v). Nút thắt cổ chai quyết định Throughput.\n- Mô hình kiến trúc phân tầng Internet có 5 tầng (Application, Transport, Network, Link, Physical), tương ứng các gói tin là Message, Segment, Datagram, Frame, và Bits. OSI model có thêm tầng Session và Presentation.\n- Có ba mối đe dọa chính là Malware, DoS/DDoS và Packet Sniffing/IP Spoofing.\n\n*Tài liệu được thiết kế riêng dành cho việc ôn thi trắc nghiệm học phần Mạng máy tính dựa trên giáo trình tiêu chuẩn Kurose & Ross.*\n"
    },
    {
      "id": "chuong_2",
      "title": "CHƯƠNG 2: TẦNG ỨNG DỤNG (APPLICATION LAYER)",
      "content": "# CHƯƠNG 2: TẦNG ỨNG DỤNG (APPLICATION LAYER)\n\n## 2.1 Nguyên lý của các ứng dụng mạng (Principles of Network Applications)\n\nTầng ứng dụng là nơi các ứng dụng mạng (network applications) và các giao thức của chúng cư trú. Phát triển một ứng dụng mạng có nghĩa là viết các chương trình phần mềm chạy trên nhiều hệ thống đầu cuối (end systems) khác nhau và giao tiếp với nhau qua mạng. Điểm cốt lõi là bạn KHÔNG cần phải viết phần mềm chạy trên các thiết bị lõi mạng (như router hay switch) vì chúng chỉ hoạt động ở các tầng thấp hơn.\n\n### 2.1.1 Các kiến trúc ứng dụng (Application Architectures)\nKhi thiết kế một ứng dụng, nhà phát triển thường chọn một trong hai mô hình kiến trúc phổ biến:\n\n**1. Kiến trúc Client-Server (Khách-Chủ):**\n- **Server (Máy chủ):** Là một host luôn luôn hoạt động (always-on), có một địa chỉ IP tĩnh cố định (permanent IP address). Nó chờ đợi các yêu cầu đến từ các client và phục vụ chúng. Khi số lượng client lớn, một server duy nhất không thể kham nổi, người ta sử dụng các cụm máy chủ (server farm/data center) để mở rộng quy mô.\n- **Client (Máy khách):** Các thiết bị của người dùng (PC, smartphone) kết nối đến server. Client không cần phải luôn luôn hoạt động và có thể thay đổi địa chỉ IP động. Đáng chú ý, trong kiến trúc này, các client KHÔNG GIAO TIẾP TRỰC TIẾP với nhau (ví dụ: trình duyệt web không liên lạc với trình duyệt web khác, chúng chỉ liên lạc với Web Server).\n\n**2. Kiến trúc P2P (Peer-to-Peer / Ngang hàng):**\n- Không có một máy chủ trung tâm luôn hoạt động.\n- Các thiết bị đầu cuối, được gọi là các nút mạng ngang hàng (peers), giao tiếp trực tiếp với nhau. Các peers thường là máy tính của người dùng bình thường.\n- Đặc tính nổi bật của P2P là **Khả năng tự mở rộng (Self-scalability):** Mỗi peer vừa là người yêu cầu dịch vụ (client) vừa là người cung cấp dịch vụ (server) cho peer khác. Ví dụ, trong BitTorrent, khi một người tải file về, họ đồng thời cũng đang upload file đó cho những người khác.\n- Nhược điểm: Phức tạp trong quản lý, bảo mật kém và phụ thuộc vào sự tự nguyện tham gia của các nút.\n\n### 2.1.2 Giao tiếp giữa các tiến trình (Processes Communicating)\nTrên một hệ điều hành, chương trình đang chạy được gọi là một **Tiến trình (Process)**. Khi hai tiến trình chạy trên cùng một máy tính, chúng giao tiếp với nhau thông qua cơ chế Inter-Process Communication (IPC) của hệ điều hành. Tuy nhiên, trong mạng máy tính, chúng quan tâm đến việc các tiến trình chạy trên HAI MÁY TÍNH KHÁC NHAU giao tiếp với nhau. Chúng thực hiện điều này bằng cách trao đổi các thông điệp (messages) qua mạng.\n\n**Socket:**\nMọi tiến trình gửi hoặc nhận thông điệp mạng thông qua một giao diện phần mềm gọi là **Socket**. Socket giống như một \"cánh cửa\" giữa tiến trình ứng dụng và giao thức vận chuyển (Transport protocol).\n- Tiến trình đẩy thông điệp ra ngoài cánh cửa (socket).\n- Nó dựa vào hạ tầng giao vận bên ngoài cánh cửa đó để mang thông điệp tới socket của tiến trình nhận.\n- Giao diện Socket là API (Application Programming Interface) giữa ứng dụng và mạng. Lập trình viên có toàn quyền kiểm soát tầng ứng dụng nhưng chỉ có một chút quyền kiểm soát đối với tầng transport (như chọn TCP hay UDP, thiết lập một số tham số bộ đệm).\n\n**Địa chỉ của Tiến trình (Addressing Processes):**\nĐể gửi thông điệp cho một tiến trình đích, hệ thống nguồn cần biết hai thông tin:\n1. **Địa chỉ IP của Host đích:** (ví dụ: 192.168.1.5) dùng để chuyển gói tin tới đúng chiếc máy tính đó.\n2. **Số hiệu Cổng (Port Number):** (ví dụ: Port 80) dùng để xác định chính xác tiến trình/ứng dụng nào trên máy tính đó sẽ nhận dữ liệu. Một máy tính có thể chạy cùng lúc Web server, Mail server, Game server... Port number là định danh cho tiến trình.\n   - HTTP Web Server mặc định dùng Port 80.\n   - HTTPS dùng Port 443.\n   - Mail Server (SMTP) dùng Port 25.\n\n### 2.1.3 Các dịch vụ mà tầng Giao vận cung cấp cho tầng Ứng dụng\nKhi ứng dụng đẩy thông điệp qua Socket, nó kỳ vọng tầng Giao vận (Transport Layer) ở dưới thực hiện việc vận chuyển. Các ứng dụng có yêu cầu khác nhau về dịch vụ giao vận, thường chia làm 4 yếu tố:\n1. **Truyền dữ liệu tin cậy (Reliable Data Transfer):** Ứng dụng như Web, Email, File transfer yêu cầu 100% dữ liệu phải tới đích không bị lỗi và không bị mất (No data loss). Nếu mạng mất gói, giao thức vận chuyển phải tự truyền lại. Ngược lại, ứng dụng âm thanh/video thời gian thực có thể chấp nhận mất một số dữ liệu (loss-tolerant).\n2. **Băng thông (Throughput):** Một số ứng dụng yêu cầu băng thông tối thiểu để hoạt động trơn tru (ví dụ Video 4K cần băng thông lớn). Chúng gọi là bandwidth-sensitive applications. Ngược lại, Elastic applications (như Email, File transfer) có thể chạy với bất kỳ băng thông nào có sẵn.\n3. **Thời gian (Timing):** Đảm bảo độ trễ (delay) từ người gửi tới người nhận phải rất thấp. Quan trọng cho ứng dụng gọi thoại (Internet telephony), game online.\n4. **Bảo mật (Security):** Mã hóa dữ liệu để chống nghe lén.\n\n---\n\n## 2.2 Các Giao thức Tầng Ứng dụng cốt lõi của Internet\n\n### 2.2.1 TCP và UDP\nInternet cung cấp 2 giao thức Transport chính cho ứng dụng sử dụng:\n- **Dịch vụ TCP (Transmission Control Protocol):** Cung cấp truyền tải tin cậy (đảm bảo không mất gói, đúng thứ tự), cung cấp cơ chế kiểm soát luồng (flow control) và kiểm soát tắc nghẽn (congestion control). TCP là giao thức Hướng kết nối (Connection-oriented), yêu cầu 2 bên thiết lập kết nối trước (qua cơ chế bắt tay 3 bước - 3-way handshake) rồi mới truyền dữ liệu.\n- **Dịch vụ UDP (User Datagram Protocol):** Rất nhẹ và đơn giản. Nó là giao thức Phi kết nối (Connectionless). UDP KHÔNG đảm bảo truyền tin cậy (gói tin có thể mất hoặc sai thứ tự), KHÔNG kiểm soát tắc nghẽn. Ưu điểm của nó là tốc độ cực nhanh, thích hợp cho Streaming Video, DNS.\n\n### 2.2.2 Web và HTTP\n**HTTP (HyperText Transfer Protocol)** là giao thức trung tâm của Web. HTTP hoạt động theo mô hình Client-Server.\n- Client (thường là Web browser) gửi HTTP Request.\n- Server (Web server như Apache, Nginx) phản hồi bằng HTTP Response chứa các đối tượng Web (HTML, ảnh, video).\n\n**Đặc điểm của HTTP:**\n- **Sử dụng TCP** làm giao thức giao vận ở tầng dưới (port 80). Nhờ vậy, HTTP không cần lo lắng về việc mất mát dữ liệu.\n- **Stateless (Phi trạng thái):** Bản thân HTTP là một giao thức phi trạng thái. Máy chủ HTTP KHÔNG lưu giữ bất kỳ thông tin nào về các yêu cầu trước đó của client. Nếu bạn gửi yêu cầu file A, rồi 2 giây sau lại yêu cầu file A, máy chủ vẫn sẽ phục vụ bạn lại từ đầu như chưa từng quen biết.\n\n**HTTP Non-persistent (Không bền bỉ) vs Persistent (Bền bỉ):**\n- *Non-persistent HTTP (HTTP/1.0):* Đối với mỗi đối tượng web (ví dụ 1 trang HTML có 10 bức ảnh), một kết nối TCP riêng biệt phải được tạo lập để tải đối tượng đó. Tải xong 1 file, kết nối TCP bị đóng. Điều này gây ra độ trễ cực lớn do phải lặp lại quá trình thiết lập kết nối (tốn RTT - Round Trip Time) cho mỗi đối tượng.\n- *Persistent HTTP (HTTP/1.1):* Máy chủ giữ cho kết nối TCP mở (open) sau khi gửi phản hồi. Các request/response tiếp theo giữa cùng một client-server được gửi qua cùng một kết nối TCP này. Giúp tiết kiệm rất nhiều RTT và CPU.\n\n**Cookies:**\nBởi vì HTTP là stateless, các trang web (như trang mua sắm trực tuyến) cần một cơ chế để theo dõi người dùng. Họ sử dụng Cookies.\nQuy trình:\n1. HTTP Response từ Server mang theo header `Set-cookie: 1678`.\n2. Browser nhận được, lưu cookie `1678` vào ổ cứng.\n3. Các HTTP Request sau này từ Browser gửi lên Server sẽ đính kèm header `Cookie: 1678`. Nhờ đó Server nhận diện được người dùng cũ.\n\n**Web Caching (Proxy Server):**\nWeb cache là một thực thể mạng lưu trữ bản sao của các trang web gần đây. Nó đứng giữa Client và Origin Server.\n- Khi Browser cần một trang, nó gửi HTTP Request tới Web Cache.\n- Nếu Cache có file đó, nó lập tức gửi lại cho Browser. (Rất nhanh)\n- Nếu Cache không có, Cache sẽ gửi Request lên Origin Server lấy file về, lưu lại 1 bản, rồi gửi cho Browser.\nMục đích của Web Cache là giảm đáng kể thời gian phản hồi (response time) cho người dùng và giảm lưu lượng giao thông trên các đường liên kết (link) truy cập ra ngoài Internet của tổ chức. HTTP có cung cấp một header `If-Modified-Since` trong Conditional GET để Cache kiểm tra xem file trên Origin Server có bị thay đổi hay chưa, để quyết định có dùng lại bản lưu nội bộ hay không.\n\n### 2.2.3 Electronic Mail (SMTP, POP3, IMAP)\nHệ thống Email có 3 thành phần chính:\n1. **User Agents (Trình đọc mail):** Như Outlook, Apple Mail.\n2. **Mail Servers:** Nơi chứa các hộp thư (mailbox) của người dùng.\n3. **SMTP (Simple Mail Transfer Protocol):** Giao thức truyền tải mail.\n\n**Quy trình gửi Email:**\nKhi Alice gửi mail cho Bob:\n1. User Agent của Alice dùng **SMTP** (sử dụng TCP port 25) để đẩy thư lên Mail Server của Alice.\n2. Mail Server của Alice đóng vai trò là SMTP Client, dùng **SMTP** chuyển thư tới Mail Server của Bob (đóng vai trò SMTP Server). Thư được lưu vào mailbox của Bob.\n3. Bob dùng một *Mail Access Protocol* (Giao thức truy xuất thư) như **POP3** (Post Office Protocol v3), **IMAP** (Internet Message Access Protocol) hoặc **HTTP** (Webmail) để tải hoặc xem thư từ Mail Server của anh ấy về User Agent của mình.\n\n**Lưu ý:** KHÔNG dùng SMTP để kéo (pull) thư từ server về máy. SMTP là một giao thức đẩy (push protocol).\n\n### 2.2.4 DNS (Domain Name System)\nTrong mạng, các router định tuyến gói tin dựa vào địa chỉ IP (ví dụ: `142.250.190.46`). Tuy nhiên, con người thích sử dụng các tên miền dễ nhớ (hostname) như `www.google.com`. Nhiệm vụ của DNS là dịch (dịch vụ phân giải) Hostname thành IP address.\n\nDNS là:\n1. Một cơ sở dữ liệu phân tán theo cấu trúc phân cấp (distributed, hierarchical database).\n2. Một giao thức tầng Ứng dụng cho phép các host truy vấn cơ sở dữ liệu này. Nó sử dụng giao thức **UDP ở port 53**.\n\n**Cấu trúc phân cấp của máy chủ DNS:**\nKhông có một máy chủ DNS nào chứa toàn bộ bản đồ Internet. Thay vào đó nó phân cấp:\n- **Root DNS Servers:** Cấp cao nhất. Trả về địa chỉ của máy chủ TLD.\n- **Top-Level Domain (TLD) Servers:** Quản lý các đuôi `.com`, `.org`, `.net`, `.vn`... Trả về địa chỉ của máy chủ Authoritative.\n- **Authoritative DNS Servers (Máy chủ có thẩm quyền):** Thuộc về các tổ chức, doanh nghiệp (như máy chủ DNS của Facebook, của trường đại học). Chứa bản đồ mapping chính xác tên miền cụ thể (vd: `www.facebook.com`) sang IP.\n\nNgoài ra còn có **Local DNS Server** (Máy chủ DNS cục bộ) do ISP cung cấp (ví dụ router wifi nhà bạn). Khi thiết bị của bạn truy vấn DNS, nó sẽ hỏi Local DNS trước. Local DNS sẽ thực hiện các truy vấn đệ quy (recursive) hoặc lặp (iterative) lên hệ thống phân cấp Root -> TLD -> Authoritative để lấy IP về cho bạn.\nDNS cũng sử dụng cơ chế Caching một cách sâu rộng để tăng tốc quá trình phân giải và giảm tải cho các Root server.\n\n### 2.2.5 P2P File Distribution (Mạng chia sẻ tệp ngang hàng)\nKhác với Client-Server nơi Server gánh toàn bộ tải truyền file, trong P2P, gánh nặng được chia sẻ cho các peers.\nGiao thức P2P nổi tiếng nhất là **BitTorrent**.\n- Trong BitTorrent, một tệp lớn được chia thành nhiều \"chunks\" (mảnh) kích thước 256KB.\n- Những người dùng tham gia tải/phân phối một file gọi chung là một **Torrent**.\n- Khi Alice tham gia một Torrent, ban đầu cô chưa có chunk nào. Cô kết nối vào mạng, hỏi danh sách các peer khác đang giữ các chunk của file từ một máy chủ theo dõi (Tracker).\n- Alice song song tải các chunk cô còn thiếu từ các peer khác, và đồng thời đẩy các chunk cô đã có cho người khác.\n- Lựa chọn Peer: BitTorrent sử dụng thuật toán \"tit-for-tat\" (hòn bấc ném đi, hòn chì ném lại). Alice sẽ ưu tiên gửi dữ liệu (unchoke) cho 4 peer nào đang gửi dữ liệu cho cô với tốc độ nhanh nhất.\n\n### 2.2.6 Video Streaming và CDN\n**HTTP Streaming (DASH):**\nNgày nay, hầu hết video (như YouTube, Netflix) được phát qua giao thức **DASH** (Dynamic Adaptive Streaming over HTTP).\n- Video được chia thành các đoạn nhỏ (ví dụ vài giây).\n- Mỗi đoạn được mã hóa (encode) ở nhiều chất lượng/độ phân giải khác nhau (bitrates).\n- Một file *Manifest* chứa danh sách các URL tương ứng với từng đoạn và từng chất lượng.\n- Client (Trình phát video) liên tục đo lường băng thông hiện tại. Tùy vào mạng đang mạnh hay yếu, Client tự động chủ động yêu cầu tải đoạn video chất lượng cao hay thấp tiếp theo (Adaptive).\n\n**CDN (Content Delivery Networks):**\nĐể cung cấp lượng dữ liệu video khổng lồ cho người dùng toàn cầu mà không bị nghẽn mạng, các công ty sử dụng CDN. CDN là các hệ thống gồm hàng ngàn máy chủ lưu trữ bản sao nội dung (cache) đặt rải ráp khắp nơi trên thế giới.\n- Khi người dùng ở Việt Nam truy cập một video của Mỹ, hệ thống DNS sẽ thông minh điều hướng (redirect) kết nối của người dùng tới cụm máy chủ CDN đặt tại Việt Nam hoặc Singapore gần đó nhất.\n- Lợi ích: Giảm độ trễ cực lớn, tăng băng thông, giảm thiểu nguy cơ nghẽn cục bộ tại server gốc.\n\n---\n## TÓM TẮT NHỮNG ĐIỂM CHÍNH (KEY TAKEAWAYS)\n- Tầng ứng dụng hoạt động thông qua socket, sử dụng IP và Port để giao tiếp.\n- Các kiến trúc: Client-Server và P2P.\n- HTTP là giao thức web (Port 80, TCP), Stateless. Có Non-persistent (tốn RTT cho mỗi file) và Persistent. Dùng Cookie để quản lý trạng thái, dùng Web Cache để tối ưu.\n- Email sử dụng SMTP (để push - Port 25, TCP), POP3/IMAP (để pull/đọc).\n- DNS phân giải tên miền sang IP, dùng UDP Port 53, cấu trúc phân cấp (Root, TLD, Authoritative).\n- P2P (BitTorrent) tự mở rộng băng thông dựa trên việc các peer đóng vai trò cả client và server. Thuật toán Tit-for-tat.\n- Video streaming dùng DASH qua HTTP và CDN để đưa nội dung đến vị trí địa lý gần người dùng nhất.\n"
    },
    {
      "id": "chuong_3",
      "title": "CHƯƠNG 3: TẦNG GIAO VẬN (TRANSPORT LAYER)",
      "content": "# CHƯƠNG 3: TẦNG GIAO VẬN (TRANSPORT LAYER)\n\n## 3.1 Dịch vụ Tầng Giao vận (Transport-Layer Services)\n\nTầng giao vận cung cấp **dịch vụ giao tiếp logic (logical communication)** trực tiếp giữa các tiến trình (processes) ứng dụng chạy trên các host khác nhau. Nhờ có dịch vụ này, dưới con mắt của ứng dụng, hai tiến trình dường như được kết nối trực tiếp với nhau, cho dù chúng có cách xa nhau nửa vòng trái đất và phải vượt qua hàng chục bộ định tuyến.\n\n### 3.1.1 Sự khác biệt giữa Network Layer và Transport Layer\nĐể hiểu rõ, hãy dùng hình ảnh ẩn dụ: Mạng lưới bưu chính.\n- *Host (Thiết bị)* là các ngôi nhà.\n- *Process (Tiến trình)* là những người sống trong nhà.\n- *Application Message (Bản tin)* là những bức thư trong phong bì.\n- *Network Layer (Tầng mạng)*: Là những người đưa thư, xe bưu điện. Chịu trách nhiệm vận chuyển bưu phẩm từ **Nhà này đến Nhà kia** (từ Host tới Host).\n- *Transport Layer (Tầng giao vận)*: Là anh chị em đại diện trong gia đình có nhiệm vụ thu thập thư từ các thành viên trong nhà gửi cho bưu điện, và nhận thư từ bưu điện để chia về tay chính xác từng người trong nhà. Nghĩa là giao vận từ **Người đến Người** (từ Process tới Process).\n\nGiao thức của Transport layer KHÔNG được phép can thiệp vào các bộ định tuyến trong lõi mạng (core routers). Nó chỉ được triển khai tại các thiết bị đầu cuối (end systems).\n- Tại host gửi: Nó cắt các Application messages ra thành nhiều phần, thêm Transport header tạo thành các **Segment** rồi đẩy xuống Network layer (IP).\n- Tại host nhận: Nó nhận các Datagram từ Network layer, lấy ra các Segment, rắp ráp lại và chuyển đến đúng ứng dụng qua Socket.\n\n### 3.1.2 Multiplexing và Demultiplexing (Ghép kênh và Phân kênh)\nLàm thế nào để Transport Layer biết chuyển dữ liệu cho ứng dụng nào trong máy (vì một máy tính có thể mở cùng lúc Web, Game, Skype)? Trả lời: Nhờ vào **Socket** và **Port Number (Số hiệu cổng)**.\n- **Demultiplexing (Phân kênh ở máy nhận):** Quá trình Transport layer kiểm tra thông tin Port Number trong Segment đến, và điều hướng Segment đó vào đúng socket của tiến trình phù hợp.\n- **Multiplexing (Ghép kênh ở máy gửi):** Quá trình thu gom dữ liệu từ nhiều socket của nhiều tiến trình, gói gọn chúng bằng cách gắn Header (có chứa Source Port và Destination Port) để tạo thành Segment, rồi chuyển xuống Network layer.\n\nSố hiệu cổng (Port) là một số 16-bit, từ 0 đến 65535. Các port từ 0 - 1023 là Well-known ports (Cổng được cấp phép chặt chẽ cho các ứng dụng tiêu chuẩn như HTTP 80, FTP 21, SSH 22).\n\n**Phân kênh không kết nối (UDP Demultiplexing):**\nSocket UDP được định danh bởi một bộ 2 thông số (two-tuple): `(Destination IP, Destination Port)`. Do đó, nếu hai máy khách A và B cùng gửi UDP segment đến cùng một IP Máy chủ, cùng Port Máy chủ (vd 53), cả hai segment này sẽ được đẩy vào chung MỘT socket duy nhất tại Máy chủ.\n\n**Phân kênh có kết nối (TCP Demultiplexing):**\nSocket TCP được định danh bằng một bộ 4 thông số (four-tuple): `(Source IP, Source Port, Destination IP, Destination Port)`. Do đó, ngay cả khi 10 máy khách cùng gửi dữ liệu đến IP Máy chủ ở Port 80, Máy chủ Web sẽ tạo ra 10 Socket khác biệt để tiếp nhận 10 luồng dữ liệu này. Đây là cốt lõi của kết nối máy chủ Web đồng thời.\n\n---\n\n## 3.2 Giao thức UDP (User Datagram Protocol)\n\nUDP (RFC 768) là giao thức tầng Giao vận ở mức tối giản nhất. Nó thực hiện công việc lấy dữ liệu từ ứng dụng, cộng thêm thông tin ghép kênh/phân kênh, thêm chức năng kiểm tra lỗi đơn giản, rồi đẩy thẳng xuống tầng Mạng.\nĐặc điểm:\n- **Phi kết nối (Connectionless):** Không có quá trình thiết lập kết nối (bắt tay) giữa bên gửi và nhận trước khi truyền. Không tốn thời gian RTT khởi tạo.\n- **Không đáng tin cậy:** Gói tin UDP gửi đi có thể bị mất, lộn xộn thứ tự.\n- **Không kiểm soát luồng, không kiểm soát tắc nghẽn:** Gửi dữ liệu ra mạng với bất kỳ tốc độ nào mà ứng dụng có thể đẩy. Gây ra hiện tượng chèn ép các TCP flows nếu UDP xả rác quá mức.\n- **Segment header rất nhỏ:** Chỉ 8 bytes (TCP header tốn 20 bytes).\n\n**Cấu trúc UDP Header (8 bytes):**\n1. Source Port (2 bytes)\n2. Destination Port (2 bytes)\n3. Length (2 bytes)\n4. Checksum (2 bytes)\n\n**UDP Checksum:** Dùng để phát hiện xem các bit trong segment có bị thay đổi (do nhiễu đường truyền vật lý hoặc lỗi bộ nhớ router) khi di chuyển từ nguồn đến đích hay không. Bên gửi tính tổng các đoạn 16-bit của gói tin, bù 1 và đặt vào trường checksum. Bên nhận cộng tất cả lại, nếu kết quả toàn bit 1 thì không có lỗi, nếu có bit 0 tức là bị lỗi và UDP thường sẽ loại bỏ gói tin đó.\n\nỨng dụng của UDP: Các ứng dụng cần phản hồi cực nhanh (DNS), đa phương tiện thời gian thực không nhạy cảm việc mất mát (Skype, VoIP, Streaming), SNMP.\n\n---\n\n## 3.3 Nguyên lý Truyền dữ liệu Tin cậy (Principles of Reliable Data Transfer - RDT)\n\nVì tầng mạng (IP) bên dưới là không tin cậy (Unreliable), giao thức vận chuyển (như TCP) phải xây dựng một ảo giác về một đường ống \"Tin cậy tuyệt đối\" ở tầng trên. Dữ liệu truyền không bao giờ bị hỏng (corrupted) và không bao giờ bị mất.\n\nĐể xây dựng RDT, các nhà thiết kế dùng các cơ chế sau:\n1. **Error Detection (Phát hiện lỗi):** Checksum để biết gói tin bị hỏng bit.\n2. **ACK/NAK (Phản hồi):** Receiver gửi gói tin báo nhận (Acknowledgement) khi nhận thành công, hoặc Negative Acknowledgement khi gói tin bị lỗi để Sender biết gửi lại.\n3. **Timeout (Hẹn giờ):** Nếu Sender gửi gói tin đi, nhưng gói tin bị mất, hoặc gói ACK báo về bị mất, Sender sẽ chờ mãi mãi? Giải pháp là Timer. Sender đặt đồng hồ đếm ngược. Nếu hết thời gian timeout mà chưa nhận được ACK, Sender sẽ tự động Retransmit (gửi lại) gói tin đó.\n4. **Sequence Number (Số thứ tự):** Khi gửi lại do timeout, Receiver có thể nhận được các bản sao lặp lại của cùng một gói tin (Duplicate packets). Để Receiver phân biệt gói mới và gói bị lặp, mỗi gói tin phải được đánh số thứ tự (Sequence number).\n\n**RDT theo nguyên lý Pipelining (Đường ống):**\nTrong giao thức RDT cơ bản như Stop-and-Wait, Sender gửi 1 gói, chờ ACK, rồi mới gửi gói 2. Điều này làm hiệu suất cực thấp vì đường truyền lớn bị bỏ trống. Giải pháp là Pipelining: Sender được phép gửi nhiều gói tin liên tiếp mà không cần chờ ACK ngay lập tức. Tuy nhiên, nó yêu cầu phải có Buffer để lưu trữ, và cơ chế đánh số thứ tự lớn hơn.\nCó 2 cách xử lý lỗi trong Pipelining:\n- **Go-Back-N (GBN):** Sender duy trì một \"cửa sổ trượt\" (sliding window) kích thước N. Nếu gói thứ K bị lỗi/mất, Receiver sẽ bỏ qua mọi gói tin K+1, K+2 gửi đến sau đó. Khi Sender bị Timeout ở gói K, nó sẽ phải gửi lại TOÀN BỘ các gói từ K đến N. GBN gửi ACK lũy kế (Cumulative ACK).\n- **Selective Repeat (SR - Phát lại có chọn lọc):** Sender chỉ gửi lại CHÍNH XÁC gói tin bị lỗi hoặc bị mất, chứ không phải gửi lại cả một loạt. Receiver có buffer để chứa các gói nhận sớm hơn thứ tự (out-of-order) và gửi các ACK riêng lẻ (Individual ACK).\n\n---\n\n## 3.4 Giao thức TCP (Transmission Control Protocol)\n\nTCP (RFC 793) cung cấp dịch vụ tin cậy, hướng kết nối, và truyền luồng byte (byte-stream).\n\n### 3.4.1 Đặc điểm cơ bản của TCP\n- **Hướng kết nối:** TCP yêu cầu thiết lập kết nối logic trước qua quá trình 3-way handshake.\n- **Full-duplex:** Truyền dữ liệu đồng thời hai chiều trên cùng một kết nối.\n- **Point-to-point:** Mỗi kết nối TCP chỉ thiết lập giữa đúng 1 Sender và 1 Receiver (không có chuyện multicasting).\n- **In-order byte stream:** Dữ liệu truyền đi dưới dạng luồng byte tuần tự.\n\n**Cấu trúc TCP Header (Thường 20 bytes):**\n- Source Port / Dest Port (4 bytes)\n- **Sequence Number (Số thứ tự - 4 bytes):** Là số hiệu của byte ĐẦU TIÊN trong luồng dữ liệu của segment này. (TCP đánh số theo bytes, không đánh số theo số lượng gói).\n- **Acknowledgment Number (Số báo nhận - 4 bytes):** Là số hiệu của byte TIẾP THEO mà máy nhận đang mong chờ (Cumulative ACK).\n- Header Length, Flags (ACK, SYN, FIN, RST, PSH, URG), Receive Window, Checksum...\n\n### 3.4.2 Quá trình Thiết lập và Đóng kết nối\n**Thiết lập (3-way Handshake):**\n1. Client gửi một **SYN segment** cho Server (Cờ SYN=1, Seq=x). Client ở trạng thái SYN_SENT.\n2. Server nhận SYN, cấp phát buffer. Phản hồi bằng **SYNACK segment** (Cờ SYN=1, ACK=1, Seq=y, Ack_num=x+1). Server chuyển sang SYN_RCVD.\n3. Client nhận SYNACK, phản hồi bằng **ACK segment** (Cờ ACK=1, Seq=x+1, Ack_num=y+1). Có thể mang theo payload dữ liệu. Client và Server chuyển sang ESTABLISHED.\n\n**Đóng kết nối (4-way Handshake):**\n1. Client gửi **FIN segment** báo muốn ngắt. Trạng thái FIN_WAIT_1.\n2. Server nhận FIN, phản hồi **ACK**. Server ở trạng thái CLOSE_WAIT. Client nhận ACK sang FIN_WAIT_2.\n3. Khi Server đã truyền xong mọi dữ liệu còn lại, nó cũng gửi **FIN segment**. Chuyển sang LAST_ACK.\n4. Client nhận FIN, phản hồi **ACK**. Client vào trạng thái TIME_WAIT (thường chờ một lúc để đảm bảo mạng xóa hết các gói lạc). Sau đó kết thúc (CLOSED). Server nhận ACK thì CLOSED ngay.\n\n### 3.4.3 TCP Reliable Data Transfer (Truyền tin cậy)\nTCP sử dụng Timer. Vậy đặt Timeout bao lâu là vừa? TCP tính toán RTT liên tục qua các mẫu (SampleRTT) để đưa ra EstimatedRTT bằng công thức trung bình có trọng số mũ EWMA (Exponential Weighted Moving Average) để làm mượt dữ liệu. TimeoutInterval = EstimatedRTT + 4 * DevRTT.\n\n**Truyền lại nhanh (Fast Retransmit):**\nChờ Timeout thường rất lâu. Tuy nhiên TCP có mẹo: Nếu Sender nhận được 3 ACK lặp lại (Duplicate ACKs) cùng một số thứ tự, nghĩa là Receiver đang gào thét \"Tôi thiếu đoạn này, các đoạn sau tới hết rồi\". Sender lập tức gửi lại ngay gói tin đó mà KHÔNG ĐỢI TIMEOUT.\n\n### 3.4.4 Flow Control (Kiểm soát luồng)\nTCP cung cấp Flow Control để ngăn Sender gửi dữ liệu QUÁ NHANH làm tràn bộ đệm nhận (receive buffer) của Receiver.\nReceiver công bố kích thước còn trống trong bộ đệm của nó cho Sender thông qua trường **Receive Window (rwnd)** trong TCP header. Sender phải giới hạn lượng dữ liệu đang bay (unacknowledged data) luôn luôn nhỏ hơn hoặc bằng rwnd.\n\n### 3.4.5 Congestion Control (Kiểm soát tắc nghẽn)\nKhác với Flow Control (bảo vệ máy nhận), **Congestion Control** bảo vệ TOÀN BỘ MẠNG LƯỚI INTERNET khỏi sự nghẽn cổ chai cục bộ tại các router. Nếu mọi người cùng bơm dữ liệu hết công suất, router nghẽn -> mất gói -> gửi lại -> nghẽn nặng hơn -> Internet sụp đổ.\n\nTCP giải quyết tắc nghẽn thông qua 3 pha chính:\n1. **Slow Start (Khởi động chậm):** Bắt đầu gửi chậm (Congestion Window `cwnd` = 1 MSS), nhưng tăng TỐC ĐỘ GẤP ĐÔI (tăng theo cấp số nhân) sau mỗi RTT. Giai đoạn này thực ra không chậm, nó thăm dò tốc độ rất gắt.\n2. **Congestion Avoidance (Tránh tắc nghẽn):** Khi `cwnd` đạt đến ngưỡng ssthresh (Slow Start Threshold), tốc độ không nhân đôi nữa mà tăng tuyến tính, cộng 1 MSS cho mỗi RTT để tránh gây ra lỗi mạng đột ngột.\n3. **Phát hiện tắc nghẽn và phản ứng:**\n   - Nếu xảy ra **Timeout**, đó là sự cố nghiêm trọng. TCP phản ứng mạnh bằng cách tụt ssthresh xuống còn một nửa `cwnd` hiện tại, và ép `cwnd` về 1 MSS. Quay lại pha Slow Start.\n   - Nếu xảy ra **3 Duplicate ACKs** (TCP Reno), có vẻ mạng vẫn hoạt động được đôi chút vì gói tin gửi sau vẫn đến đích. TCP giảm một nửa ssthresh, và đưa `cwnd` bằng giá trị ssthresh mới cộng thêm 3 (Fast Recovery), tăng tuyến tính trở lại.\n\nSự hoạt động của TCP Congestion Control khiến cho đồ thị throughput của nó có hình răng cưa (Saw-tooth behavior) - AIMD (Additive Increase, Multiplicative Decrease).\n\n---\n## TÓM TẮT (KEY TAKEAWAYS)\n- Tầng giao vận kết nối tiến trình-tiến trình (Process-to-process).\n- Multiplexing/Demultiplexing qua IP và Port. UDP dùng 2-tuple, TCP dùng 4-tuple.\n- UDP phi kết nối, không tin cậy. Dùng cho Streaming/DNS. Checksum 1s complement.\n- RDT giải quyết môi trường lỗi qua: Checksum, ACK, Timer (Timeout), Sequence Number. Kỹ thuật pipelining: Go-Back-N (Ack lũy kế) và Selective Repeat (Ack độc lập).\n- TCP thiết lập kết nối 3 bước (SYN, SYNACK, ACK), ngắt 4 bước (FIN). Đánh số thứ tự theo byte stream.\n- Fast Retransmit khi có 3 Dup ACKs.\n- Flow Control dùng biến rwnd (Window size).\n- Congestion Control: Tránh nghẽn router, với 3 trạng thái Slow Start, Congestion Avoidance, Fast Recovery. Hành vi đặc trưng AIMD (Răng cưa).\n"
    },
    {
      "id": "chuong_4",
      "title": "CHƯƠNG 4: TẦNG MẠNG (NETWORK LAYER) - DATA PLANE VÀ CONTROL PLANE",
      "content": "# CHƯƠNG 4: TẦNG MẠNG (NETWORK LAYER) - DATA PLANE VÀ CONTROL PLANE\n\nTầng mạng (Network Layer) là tầng phức tạp nhất trong toàn bộ mô hình TCP/IP vì nó liên quan đến TẤT CẢ các thiết bị đầu cuối và TẤT CẢ các bộ định tuyến (router) tạo nên mạng lưới toàn cầu Internet.\nChức năng duy nhất và quan trọng nhất của tầng mạng là: **Chuyển các gói tin (Datagram) từ host gửi (sender) đến host nhận (receiver)**.\n\nĐể làm được điều đó, mạng lưới chia các chức năng của router thành 2 mặt phẳng hoàn toàn tách biệt: Data Plane và Control Plane.\n\n---\n\n## 4.1 Data Plane (Mặt phẳng Dữ liệu) và Chức năng Forwarding\n\nData Plane (Mặt phẳng dữ liệu) phụ trách xử lý công việc \"địa phương\" ngay bên trong mỗi router đơn lẻ. Chức năng chính của nó là **Forwarding (Chuyển tiếp)**.\n- **Forwarding:** Là hành động vật lý khi một router lấy gói tin từ cổng đầu vào (input link) và đẩy gói tin đó sang cổng đầu ra (output link) thích hợp. Nó diễn ra trong khoảng thời gian siêu ngắn (nanoseconds) và thường được thực thi cứng bằng phần cứng (Hardware).\n- Khi gói tin tới, router sẽ trích xuất một phần thông tin trong header (chẳng hạn như địa chỉ IP đích). Sau đó router tra cứu trong **Bảng chuyển tiếp (Forwarding Table)** để tìm cổng đầu ra tương ứng.\n\n### 4.1.1 Kiến trúc bên trong của Router\nRouter gồm 4 thành phần chính:\n1. **Input Ports (Cổng đầu vào):** Thực hiện kết thúc liên kết vật lý (physical layer), xử lý liên kết dữ liệu (link layer), và tra cứu (lookup) xem gói tin phải chuyển ra cổng nào dựa vào Forwarding table. Nếu gói tin đến quá nhanh, cổng vào sẽ đưa gói tin vào hàng đợi (Input Queue).\n2. **Switching Fabric (Mạng chuyển mạch lõi):** Trái tim của router. Nó là hệ thống kết nối vật lý nối tất cả cổng đầu vào với tất cả cổng đầu ra. Có 3 kiểu Switching Fabric: Chuyển mạch qua Memory (bộ nhớ), qua Bus (đường truyền chung), qua Crossbar (ma trận).\n3. **Output Ports (Cổng đầu ra):** Nhận các gói tin từ switching fabric, đưa vào hàng đợi nếu cần, xử lý liên kết dữ liệu và đẩy tín hiệu ra vật lý.\n4. **Routing Processor (Bộ xử lý định tuyến):** Bộ脑 thực hiện chức năng Control Plane, tính toán các thuật toán định tuyến, cấu hình Forwarding Table cho các cổng.\n\n### 4.1.2 Đóng gói ở tầng Mạng (IP Datagram)\nGiao thức cốt lõi của Data Plane Internet là **IPv4 (Internet Protocol version 4)** và **IPv6**.\nĐơn vị dữ liệu của tầng mạng gọi là Datagram.\n\n**Cấu trúc IPv4 Datagram Header (Cơ bản 20 bytes):**\n- **Version (4 bits):** Phiên bản IP (IPv4 hay IPv6).\n- **Header Length (4 bits):** Độ dài header.\n- **TOS - Type of Service (8 bits):** Mức độ ưu tiên.\n- **Datagram Length (16 bits):** Tổng độ dài của header và payload (Tối đa 65,535 bytes).\n- **Identifier, Flags, Fragmentation Offset (32 bits):** Các trường dùng cho phân mảnh (Fragmentation) các gói tin quá lớn.\n- **TTL - Time-To-Live (8 bits):** Chỉ số \"Sống sót\". Mỗi khi gói tin đi qua một router, TTL giảm đi 1. Nếu TTL = 0, router sẽ tiêu diệt gói tin để tránh trường hợp gói tin lặp vòng lặp (routing loop) vĩnh viễn trên mạng.\n- **Protocol (8 bits):** Xác định giao thức tầng Giao vận ở payload là gì (TCP = 6, UDP = 17).\n- **Header Checksum (16 bits):** Kiểm tra lỗi cho Header IP.\n- **Source IP Address (32 bits):** Địa chỉ nguồn.\n- **Destination IP Address (32 bits):** Địa chỉ đích (Rất quan trọng cho Forwarding).\n\n### 4.1.3 Phân mảnh IP (IP Fragmentation)\nMỗi liên kết mạng tầng dưới (VD: Ethernet) có một quy định về kích thước khung lớn nhất được phép gọi là MTU (Maximum Transmission Unit). Thông thường MTU là 1500 bytes.\nNếu IP Datagram có kích thước 4000 bytes, Router bắt buộc phải băm nó ra thành 3 mảnh (fragments) nhỏ hơn để chui lọt qua MTU. Quá trình chia nhỏ này gọi là Phân mảnh.\n- Đáng chú ý: Quá trình Rắp ráp (Reassembly) các mảnh này lại thành Datagram nguyên vẹn KHÔNG diễn ra ở các Router tiếp theo, mà chỉ được thực hiện tại Host nhận cuối cùng (Destination).\n\n---\n\n## 4.2 Địa chỉ IPv4 (IPv4 Addressing)\n\nMọi host và router giao diện mạng (interface) phải có địa chỉ IP để tham gia Internet. Địa chỉ IPv4 dài **32 bits** (thường viết dưới dạng 4 số thập phân cách nhau bởi dấu chấm, ví dụ: `192.168.1.1`).\n\n### 4.2.1 Subnet (Mạng con) và Mặt nạ mạng (Subnet Mask)\nMạng Internet không nhìn IP như một số ngẫu nhiên. Nó chia IP làm 2 phần: **Subnet part** (Phần định danh mạng) và **Host part** (Phần định danh máy trong mạng).\nĐể biết đâu là phần Subnet, người ta dùng Subnet Mask.\nTheo quy chuẩn **CIDR (Classless Inter-Domain Routing)**, IP được viết dưới dạng `a.b.c.d/x`, trong đó `x` là số bit làm tiền tố mạng (network prefix).\n- Ví dụ: `192.168.1.0/24` nghĩa là 24 bit đầu tiên là địa chỉ Subnet.\n- Mọi thiết bị gắn vào chung một bộ chuyển mạch (LAN) mà không đi qua router thì phải nằm trong chung 1 Subnet.\n\n### 4.2.2 DHCP (Dynamic Host Configuration Protocol)\nLàm sao một máy tính mới nối cáp vào mạng lại có địa chỉ IP? Có thể cài tĩnh (Manual), hoặc cấp phát động bằng DHCP.\nDHCP là giao thức ứng dụng (dùng UDP) thực hiện theo 4 bước (DORA):\n1. **D**iscover: Host gửi gói tin broadcast \"Ai là DHCP server?\".\n2. **O**ffer: DHCP Server trả lời \"Tôi đây, bạn dùng IP này nhé\".\n3. **R**equest: Host gửi \"Ok, tôi xin lấy IP đó\".\n4. **A**CK: Server xác nhận \"IP đó giờ là của bạn, xài trong 24h nhé\".\nDHCP cung cấp không chỉ IP, mà còn cung cấp Subnet mask, IP của Router mặc định (Default Gateway) và địa chỉ DNS server.\n\n### 4.2.3 NAT (Network Address Translation)\nCạn kiệt địa chỉ IPv4 là một vấn đề lớn (chỉ có khoảng 4 tỷ địa chỉ). NAT là giải pháp tạm thời cứu sống Internet.\nMột mạng gia đình dùng NAT, cục router được cấp đúng 1 địa chỉ IP Public cho toàn bộ nhà giao tiếp với Internet. Nhưng bên trong nhà, Router dùng DHCP phát cho các máy tính các địa chỉ IP Private cục bộ (ví dụ: `10.0.0.0/8`, `192.168.x.x`).\n- Khi một gói tin từ máy cục bộ đi ra ngoài, Router sẽ thay thế IP Nguồn (Private IP) và Port Nguồn thành IP Public của nó và một Port Nguồn do nó tự sinh ra. Nó lưu lại bảng dịch này (NAT Translation Table).\n- Khi có gói tin phản hồi về mang địa chỉ IP Public và Port đó, Router dò bảng NAT và tự động dịch ngược lại đẩy về đúng máy cục bộ.\nNAT bị lên án vì vi phạm quy tắc \"Network layer không đụng vào Port của Transport layer\", phá vỡ tính end-to-end. Tuy nhiên nó rất phổ biến.\n\n### 4.2.4 IPv6\nĐể thay thế IPv4, IPv6 ra đời với không gian địa chỉ khổng lồ **128 bits**.\n- Header IPv6 được tối giản, cố định độ dài là 40 bytes.\n- Không có trường Checksum ở IPv6 để tăng tốc độ xử lý router.\n- IPv6 KHÔNG cho phép router phân mảnh gói tin trên đường truyền. Nếu quá lớn, router drop gói và báo lỗi ICMP để máy gửi tự chia nhỏ.\n\nSự chuyển đổi IPv4 lên IPv6 quá chậm. Giải pháp phổ biến để tương thích là **Tunneling (Đường hầm)**: Gói tin IPv6 được đóng gói, nhét vào bên trong phần payload của gói tin IPv4 để đi qua những router chỉ hiểu IPv4.\n\n---\n\n## 4.3 Control Plane (Mặt phẳng Điều khiển) và Routing\n\nMặt phẳng điều khiển (Control Plane) là bộ não của mạng lưới. Chức năng chính của nó là **Routing (Định tuyến)**.\n- **Routing:** Xác định ĐƯỜNG ĐI TOÀN CỤC (path) cho các gói tin từ nguồn tới đích đi qua mạng lưới các bộ định tuyến. Thuật toán định tuyến tính toán và từ đó đổ cấu hình xuống bảng chuyển tiếp (Forwarding table) của từng router ở mặt phẳng dữ liệu.\n\nCó 2 cách tiếp cận cấu trúc Control Plane:\n1. **Theo hướng truyền thống (Per-router control):** Mỗi router đều có một bộ não điều khiển chạy chung một thuật toán định tuyến để tự cấu hình forwarding table cho chính mình (như OSPF, BGP).\n2. **Theo hướng SDN (Software-Defined Networking):** Tách não (Control Plane) ra khỏi cơ bắp (Router). Bảng chuyển tiếp được tính toán tại một hệ thống Máy chủ điều khiển từ xa (Remote Controller). Router chỉ việc nhận bảng này về và làm nhiệm vụ đẩy gói tin.\n\n### 4.3.1 Các Thuật toán Định tuyến (Routing Algorithms)\nMạng lưới router được biểu diễn như một đồ thị Graph G = (N, E), với N là nút, E là cạnh (chi phí). Thuật toán tìm đường đi ngắn nhất giữa nguồn và đích.\nCó 2 nhóm thuật toán chính:\n**1. Thuật toán Trạng thái Liên kết (Link State - LS):**\n- *Kiến thức toàn cục:* Router phải có toàn bộ cấu trúc mạng lưới, biết chi phí của tất cả các liên kết bằng cách phát tán thông điệp quảng bá cho tất cả các nút (Link State Broadcast).\n- Chạy thuật toán **Dijkstra** trên cơ sở dữ liệu đó để tính đường đi ngắn nhất.\n- Giao thức thực tế: **OSPF (Open Shortest Path First)**.\n\n**2. Thuật toán Vector Khoảng cách (Distance Vector - DV):**\n- *Kiến thức cục bộ:* Router không biết toàn bộ mạng. Nó chỉ biết chi phí kết nối tới người láng giềng kề cận nó, và nhận bảng thông tin từ người láng giềng đó.\n- Sử dụng phương trình **Bellman-Ford**: Khoảng cách ngắn nhất từ x đến y = min (chi phí từ x tới v + khoảng cách ngắn nhất từ v tới y).\n- Giao thức thực tế: **RIP, BGP**.\n- Nhược điểm: Phản ứng chậm khi liên kết bị đứt, dễ bị lỗi \"Đếm đến vô cùng\" (Count-to-infinity).\n\n### 4.3.2 Định tuyến nội vùng (Intra-AS) và Định tuyến liên vùng (Inter-AS)\nInternet quá lớn, không thể để mọi router biết mọi đường đi (bảng định tuyến sẽ tốn hàng Terabytes và việc tìm kiếm cực lâu). Mạng Internet được phân chia thành các Hệ thống tự trị (Autonomous Systems - AS), mỗi AS do một tổ chức/ISP (như Viettel) quản lý.\n\n1. **Intra-AS Routing (Định tuyến nội vùng):**\n- Là việc tìm đường đi giữa các router nằm TRONG CÙNG MỘT AS. Người quản trị mạng toàn quyền quyết định thuật toán.\n- Giao thức tiêu biểu là **OSPF** (Link State) và **RIP** (Distance Vector).\n\n2. **Inter-AS Routing (Định tuyến liên vùng):**\n- Là việc tìm đường đi cho một gói tin đi GIỮA CÁC AS (VD: Gói tin từ mạng FPT sang mạng của AT&T ở Mỹ).\n- Giao thức DUY NHẤT kết dính Internet toàn cầu là **BGP (Border Gateway Protocol)**.\n- BGP không hoàn toàn tìm đường đi ngắn nhất, mà nó định tuyến dựa trên **CHÍNH SÁCH (Policy)** và kinh tế. AS quyết định sẽ định tuyến gói tin theo đường nào đem lại lợi nhuận, hoặc chặn không cho lưu lượng của kẻ thù mượn đường cáp của mình.\n- BGP quảng bá khả năng tiếp cận (Reachability) của các Subnet. Một BGP router thông báo \"Tôi có thể đi đến mạng `192.168.0.0/16` thông qua đường đi (AS-PATH) gồm các AS 1, AS 4, AS 7\".\n\n---\n## TÓM TẮT (KEY TAKEAWAYS)\n- Network layer: Data Plane (Forwarding - cục bộ ở router, chuyển từ input ra output) và Control Plane (Routing - tìm đường toàn cục).\n- IPv4 (32 bit), IPv6 (128 bit). Cấu trúc packet (Datagram).\n- Chức năng trường TTL: Diệt gói lặp vòng. Checksum: Bắt lỗi.\n- NAT che giấu toàn bộ IP Private, chia sẻ 1 IP Public bằng cách sửa Port.\n- DHCP cấp IP động, Subnet Mask chia mạng con.\n- Thuật toán định tuyến: Link State (Biết toàn cục mạng, Dijkstra, OSPF) và Distance Vector (Chỉ giao tiếp láng giềng, Bellman-Ford, BGP).\n- BGP kết nối các AS bằng định tuyến theo chính sách. OSPF định tuyến theo chi phí trong một AS.\n"
    },
    {
      "id": "chuong_5",
      "title": "CHƯƠNG 5: TẦNG LIÊN KẾT (DATA LINK LAYER) VÀ MẠNG LAN",
      "content": "# CHƯƠNG 5: TẦNG LIÊN KẾT (DATA LINK LAYER) VÀ MẠNG LAN\n\nNếu tầng Mạng (IP) phụ trách việc tìm đường từ thiết bị A tới thiết bị B xuyên qua toàn bộ Internet, thì **Tầng Liên Kết Dữ Liệu (Link Layer)** chỉ chịu trách nhiệm chuyển dữ liệu (Datagram) từ **một nút mạng sang nút mạng ngay kề cận nó** (như từ PC tới Switch, hoặc từ Switch tới Router) qua một đường liên kết vật lý đơn lẻ (single link).\nĐơn vị dữ liệu của tầng này là **Frame (Khung)**.\n\n---\n\n## 5.1 Các dịch vụ của Tầng Liên Kết\n1. **Đóng khung (Framing):** Đóng gói IP Datagram vào trong thân một Frame. Header của Frame sẽ chứa thông tin về địa chỉ vật lý nguồn và đích.\n2. **Kiểm soát truy cập đường truyền (Link Access):** Nếu nhiều thiết bị cùng sử dụng chung một môi trường truyền thông (như sóng Wi-Fi hoặc một cáp đồng trục chung), giao thức Medium Access Control (MAC) sẽ quy định lúc nào ai được phép phát tín hiệu lên cáp.\n3. **Chuyển giao tin cậy (Reliable Delivery):** Cung cấp cơ chế ACK và gửi lại tương tự TCP, nhưng chỉ áp dụng trên từng liên kết (ví dụ trên liên kết Wi-Fi rất hay bị nhiễu). Tuy nhiên, trên liên kết cáp quang hay cáp đồng xoắn (rất ít lỗi), tầng Link thường KHÔNG cung cấp tính năng này để giảm gánh nặng xử lý.\n4. **Phát hiện lỗi (Error Detection) và Sửa lỗi (Correction):** Sử dụng các bit kiểm tra lỗi (Parity, CRC) ở cuối Frame để phần cứng bên nhận dò xem tín hiệu điện từ có bị sai lệch bit nào không.\n\nTầng Link được cài đặt 100% bằng PHẦN CỨNG trên một con chip gọi là **Card mạng (Network Interface Card - NIC)**. Mọi thứ diễn ra ở phần cứng để đạt tốc độ cao nhất.\n\n---\n\n## 5.2 Kỹ thuật Phát hiện và Sửa lỗi (Error-Detection and -Correction)\n\nKhi tín hiệu điện đi qua cáp, nó có thể bị nhiễu lật bit (0 thành 1). Máy nhận cần biết gói tin có bị sai không.\n1. **Kiểm tra chẵn lẻ (Parity Checks):**\n   - *Đơn chiều:* Thêm 1 bit vào cuối chuỗi dữ liệu sao cho tổng số bit 1 là một số chẵn. Máy nhận đếm số bit 1, nếu ra số lẻ tức là có 1 bit bị lỗi. Không phát hiện được nếu 2 bit cùng lỗi.\n   - *Hai chiều (2D Parity):* Sắp dữ liệu thành ma trận, kiểm tra chẵn lẻ theo hàng và cột. Phương pháp này không những phát hiện được lỗi mà còn **chỉ ra chính xác bit nào bị lỗi để tự động SỬA LỖI (FEC - Forward Error Correction)** mà không cần yêu cầu gửi lại.\n2. **Tổng kiểm tra (Checksum):** Giống tầng Giao vận (UDP/TCP checksum).\n3. **Kiểm tra phần dư tuần hoàn (CRC - Cyclic Redundancy Check):** Rất mạnh và phổ biến trong phần cứng Ethernet. Coi chuỗi bit dữ liệu như một đa thức nhị phân. Chia đa thức này cho một chuỗi bit chuẩn (Generator G), phần dư (remainder) của phép chia chính là mã CRC (thường 32 bit). Bên nhận thực hiện phép chia tương tự, nếu số dư bằng 0 là dữ liệu toàn vẹn.\n\n---\n\n## 5.3 Giao thức Truyền thông Đa truy cập (Multiple Access Protocols)\n\nKhi nhiều máy tính kết nối vào CÙNG MỘT môi trường truyền dẫn (Broadcast link) như cáp đồng trục chung hay sóng Wi-Fi, nếu 2 máy cùng phát tín hiệu cùng lúc, tín hiệu sẽ hòa vào nhau và gây ra **Xung đột (Collision)**. Lẽ dĩ nhiên là cả 2 khung dữ liệu đều hỏng.\nCác giao thức Đa truy cập giải quyết bài toán: Phân chia tài nguyên môi trường này như thế nào? Có 3 nhóm chính:\n\n### 5.3.1 Nhóm Chia sẻ Kênh (Channel Partitioning)\n- **TDM (Time Division) / FDM (Frequency Division):** Chia nhỏ thời gian hoặc băng tần và cấp cố định cho từng máy. Ưu điểm là công bằng, không bao giờ có xung đột. Nhược điểm là lãng phí: Nếu chỉ có 1 máy cần truyền, nó cũng chỉ được dùng 1 phần băng thông của mình.\n\n### 5.3.2 Nhóm Truy cập Ngẫu nhiên (Random Access)\n- Không cấp cố định. Ai có dữ liệu thì cứ phát luôn với tốc độ tối đa của liên kết. Nếu xảy ra xung đột, họ sẽ chờ một khoảng thời gian NGẪU NHIÊN rồi phát lại.\n- **ALOHA & Slotted ALOHA:** Các giao thức nguyên thủy. Hiệu suất (Efficiency) rất thấp, chỉ khoảng 18% đến 37% băng thông thực tế được dùng hữu ích.\n- **CSMA/CD (Carrier Sense Multiple Access with Collision Detection):** Dùng trong Ethernet có dây.\n  - *Carrier Sense (Nghe trước khi nói):* Máy tính lắng nghe đường truyền. Nếu thấy có sóng (có người đang nói), nó sẽ ĐỢI cho đến khi rảnh mới phát.\n  - *Collision Detection (Phát hiện xung đột):* Trong lúc đang phát tín hiệu, thiết bị vẫn liên tục đo lường mức điện áp trên cáp. Nếu điện áp tăng vọt bất thường, nó hiểu là có một thiết bị khác cũng vừa phát tín hiệu dẫn đến va chạm. Nó LẬP TỨC NGỪNG PHÁT để tiết kiệm thời gian (thay vì cố phát hết khung) và gửi tín hiệu Jamming để báo cho mọi người biết.\n  - *Binary Exponential Backoff:* Sau khi xung đột, máy tính chọn ngẫu nhiên thời gian chờ từ tập {0, 1, 2, ..., 2^n - 1} lần slot time (với n là số lần xung đột liên tiếp). Nghĩa là càng va chạm nhiều, nó càng lùi lại chờ lâu hơn.\n- **CSMA/CA (Collision Avoidance):** Dùng trong Wi-Fi không dây.\n\n### 5.3.3 Nhóm Chuyển lượt (Taking-Turns)\n- **Polling (Thăm dò):** Có 1 máy chủ (Master) lần lượt hỏi từng máy con \"Bạn có gì cần gửi không?\". Khắc phục xung đột, nhưng Master chết thì cả mạng sụp.\n- **Token Passing (Chuyển thẻ bài):** Một \"thẻ bài\" (token) được truyền vòng tròn giữa các máy. Máy nào giữ thẻ bài mới được quyền phát dữ liệu. Không cần Master. Mạng Token Ring từng rất thịnh hành của IBM.\n\n---\n\n## 5.4 Địa chỉ MAC và Giao thức ARP\n\nTrong tầng mạng, chúng ta dùng địa chỉ IP (32 bit, logic, có tính cấu trúc phân cấp).\nTrong tầng liên kết, chúng ta dùng địa chỉ vật lý, gọi là **MAC Address (Media Access Control Address)**.\n- Địa chỉ MAC có chiều dài **48 bit** (6 bytes), thường được viết dưới dạng hệ thập lục phân, ví dụ: `1A-23-F9-CD-06-9B`.\n- Địa chỉ MAC là **Phẳng (Flat)** và **Độc nhất vô nhị (Unique)**. Nó được nhà sản xuất ghi cứng (burned) vào bộ nhớ ROM của con chip Card mạng (NIC). Dù bạn mang laptop từ Việt Nam sang Mỹ, MAC không đổi (nhưng IP sẽ đổi theo mạng Mỹ).\n- Giống như IP là địa chỉ nhà/mã bưu chính (chỉ ra khu vực bạn sống), còn MAC là Số chứng minh nhân dân (định danh cơ thể bạn bất kể bạn ở đâu).\n\n### Giao thức phân giải địa chỉ ARP (Address Resolution Protocol)\nKhi Máy A cần gửi Datagram cho Máy B (A đã biết IP của B thông qua DNS), nhưng để đóng khung (Frame) ở tầng Liên kết, A BẮT BUỘC phải biết địa chỉ MAC của B. Làm sao để tìm ra?\nGiao thức ARP là cầu nối giữa IP và MAC:\n1. Máy A kiểm tra **Bảng ARP (ARP Table)** nội bộ xem có mapping của IP B sang MAC chưa.\n2. Nếu chưa, Máy A tạo một gói tin **ARP Query**. Gói tin này chứa câu hỏi \"Ai có IP x.x.x.x, hãy trả lời gửi MAC cho tôi\".\n3. A đóng gói tin truy vấn vào một Frame với địa chỉ Đích là **Địa chỉ Broadcast (FF-FF-FF-FF-FF-FF)**. Switch sẽ nhận lệnh này và phát tán (broadcast) frame ra TẤT CẢ các cổng mạng LAN.\n4. Mọi máy tính đều nhận được, nhưng chỉ có Máy B (có IP khớp với truy vấn) mới phản hồi bằng một **ARP Response** ghi địa chỉ MAC của nó và gửi đích danh (unicast) lại cho A.\n5. A lưu lại vào ARP Table và dùng MAC đó để đóng khung dữ liệu.\n\n*Lưu ý: ARP chỉ hoạt động TRONG PHẠM VI MỘT MẠNG CỤC BỘ (Subnet/LAN). Nếu A muốn gửi gói tin cho C ở một mạng khác, A không tìm MAC của C, mà A sẽ dùng ARP để tìm MAC của Cổng Router mặc định (Default Gateway). Gói tin sẽ được Frame chuyển tới Router.*\n\n---\n\n## 5.5 Mạng Ethernet và Bộ chuyển mạch (Switch)\n\n**Ethernet** là công nghệ mạng cục bộ (LAN) có dây phổ biến nhất thế giới. Nó quy định các chuẩn cáp (như Cáp đồng xoắn đôi 100Base-T, 1000Base-T Gigabit) và cấu trúc Frame.\n\n**Cấu trúc Ethernet Frame:**\n- **Preamble (8 bytes):** Các chuỗi bit 101010.. dùng để đồng bộ hóa xung nhịp (clock) giữa máy gửi và nhận.\n- **Dest MAC & Source MAC (6 bytes mỗi trường)**\n- **Type (2 bytes):** Chỉ định giao thức tầng mạng bên trong thân (thường là IPv4, IPv6, ARP).\n- **Data (Payload - 46 đến 1500 bytes):** Kích thước tối thiểu là 46 bytes, tối đa MTU là 1500.\n- **CRC (4 bytes):** Kiểm tra lỗi.\n\nEthernet là công nghệ Phi kết nối (Connectionless) và Không tin cậy (Unreliable - không có ACK/NACK).\n\n### Bộ chuyển mạch Tầng Link (Link-Layer Switch)\nSwitch là một thiết bị thông minh (plug-and-play), hoạt động ở Tầng 2. Nó có vai trò nhận Ethernet frame ở cổng vào và đẩy (forward) ra cổng ra chính xác tới máy đích. Khác với Hub (một thiết bị ngu ngốc nhân bản tín hiệu điện ra mọi cổng gây xung đột mạng), Switch chia tách các miềm xung đột (collision domains).\n\n**Switch hoạt động ra sao? Nó học (Self-Learning) như thế nào?**\nBên trong Switch có một **Bảng Switch (Switch Table)** dùng để ánh xạ (MAC Address -> Cổng số mấy). Ban đầu bảng này trống rỗng.\n1. Khởi động, A gửi khung cho B. Khung vào cổng số 1.\n2. **Switch học:** Nó nhìn MAC NGUỒN của khung (là A), và ghi vào bảng: \"MAC A nằm ở Cổng số 1\".\n3. **Switch chuyển tiếp (Forwarding):** Nó nhìn MAC ĐÍCH của khung (là B). Vì chưa biết B ở đâu, nó **Phát tán (Flood)** khung đó ra TẤT CẢ các cổng còn lại (trừ cổng 1).\n4. Máy B nhận khung và phản hồi lại A. Khung phản hồi vào cổng 3.\n5. Switch lại học: Ghi \"MAC B nằm ở Cổng 3\". Đồng thời nó thấy MAC đích của khung là A. Nó tra bảng thấy A ở cổng 1, lập tức nó **chỉ đẩy khung ra cổng 1 (Selective Forwarding)** chứ không Flood nữa.\n\n### VLAN (Virtual Local Area Network)\nTrong các tổ chức lớn, mạng LAN bị chia nhỏ thành các mạng LAN ảo (VLAN) NGAY TRÊN CÙNG MỘT CƠ SỞ HẠ TẦNG SWITCH VẬT LÝ để dễ quản lý, tăng bảo mật và cô lập lượng truy cập Broadcast. Thiết bị thuộc VLAN kế toán không thể liên lạc trực tiếp với VLAN kỹ thuật dù cắm chung một Switch (phải đi vòng qua Router).\nĐể nối thông nhiều VLAN qua nhiều Switch với chỉ 1 sợi cáp vật lý (Trunk port), IEEE dùng chuẩn 802.1Q: chèn thêm một VLAN tag (4 bytes) vào Ethernet Frame.\n"
    },
    {
      "id": "chuong_6",
      "title": "CHƯƠNG 6: MẠNG KHÔNG DÂY VÀ DI ĐỘNG (WIRELESS AND MOBILE NETWORKS)",
      "content": "# CHƯƠNG 6: MẠNG KHÔNG DÂY VÀ DI ĐỘNG (WIRELESS AND MOBILE NETWORKS)\n\nSự bùng nổ của máy tính xách tay và điện thoại thông minh đã biến mạng không dây và di động trở thành môi trường kết nối phổ biến nhất hành tinh. Hai khái niệm \"Không dây\" (Wireless) và \"Di động\" (Mobility) thường đi chung nhưng chúng là hai khía cạnh khác nhau:\n- **Không dây:** Chỉ phương thức kết nối vật lý (sóng điện từ radio) thay vì cáp. Máy tính để bàn có thể dùng Wi-Fi nhưng nó không di chuyển.\n- **Di động:** Thiết bị di chuyển từ trạm phát sóng này sang trạm phát sóng khác nhưng vẫn yêu cầu giữ được các kết nối (TCP, cuộc gọi thoại) không bị ngắt.\n\n---\n\n## 6.1 Mạng vô tuyến (Wireless Links) và Các đặc điểm\n\nTrong mạng có dây, tín hiệu điện truyền trong ống cáp bị cô lập tốt. Trong mạng không dây, sóng phát vào không gian tự do, chia sẻ chung một \"bầu khí quyển\", do đó nó gặp phải nhiều thách thức vật lý hơn:\n\n1. **Giảm thiểu cường độ tín hiệu (Path Loss / Suy hao):** Sóng vô tuyến truyền qua vật chất (tường bê tông, cây cối, khoảng cách) cường độ tín hiệu sẽ bị giảm dần. Ngay cả trong không gian tự do, tín hiệu cũng yếu đi theo tỷ lệ nghịch với bình phương khoảng cách.\n2. **Nhiễu từ các nguồn khác (Interference):** Vì mạng không dây dùng chung một số băng tần nhất định (như dải tần ISM 2.4 GHz được dùng cho cả Wi-Fi, Bluetooth và... lò vi sóng), chúng rất dễ bị nhiễu do va chạm với các sóng điện từ khác.\n3. **Phản xạ đa đường (Multipath propagation):** Sóng radio khi dội vào trần nhà, tường, vật thể sẽ tách thành nhiều phiên bản truyền theo nhiều quỹ đạo dài ngắn khác nhau. Các bản sao tín hiệu này sẽ đến máy nhận ở các thời điểm hơi chênh lệch, gây ra nhiễu và méo dạng tín hiệu gốc.\n\n**Signal-to-Noise Ratio (SNR) và Bit Error Rate (BER):**\n- SNR (Tỉ số tín hiệu trên nhiễu) càng LỚN thì chất lượng tín hiệu càng tốt, người nhận càng dễ trích xuất thông tin gốc.\n- BER (Tỷ lệ lỗi bit) là tỷ lệ bit bị sai lệch.\n- Mối quan hệ: Khi SNR tăng, BER sẽ giảm.\n- Để chống lại BER cao trong môi trường vô tuyến yếu, người ta có thể điều chỉnh kỹ thuật điều chế (Modulation). Nếu mạng tốt, dùng điều chế phức tạp (truyền nhanh). Nếu mạng yếu, thiết bị tự lùi về điều chế cơ bản (chậm nhưng chắc chắn).\n\n### Hiện tượng Terminal ẩn (Hidden Terminal Problem)\nGiả sử có máy A, B, C. Trạm phát AP (Access Point) nằm ở B. Cả A và C đều nằm trong tầm sóng của B, nhưng A và C nằm cách xa nhau ngoài tầm của nhau.\n- A nghe thấy không có sóng, liền phát gói tin cho B.\n- C cũng nghe thấy xung quanh không có sóng (do không nghe được A), C liền phát gói tin cho B.\n- Kết quả: Xung đột xảy ra tại B.\nĐây là một vấn đề đau đầu trong mạng không dây mà công nghệ CSMA/CD của Ethernet có dây không thể áp dụng được (vì các máy không thể nghe thấy nhau truyền).\n\n---\n\n## 6.2 Wi-Fi: Chuẩn mạng cục bộ không dây (IEEE 802.11)\n\nWi-Fi (Wireless LAN) là công nghệ kết nối các thiết bị với điểm truy cập (Access Point - AP / Router Wi-Fi) trong phạm vi khoảng vài chục mét. Các chuẩn phổ biến: 802.11b, g, n (chạy ở dải tần 2.4 GHz) và 802.11a, ac, ax (chạy ở dải tần 5 GHz).\n\n### 6.2.1 Kiến trúc 802.11\n- Khối xây dựng cơ bản là một **BSS (Basic Service Set)**.\n- Một BSS điển hình ở chế độ infrastructure (cơ sở hạ tầng) bao gồm một điểm truy cập trung tâm (AP) và các thiết bị không dây (laptop, điện thoại). AP được nối dây cáp vào một router/switch nối ra Internet.\n- Mỗi AP được gắn một mã định danh **SSID (Service Set Identifier)** - chính là cái Tên Mạng Wi-Fi mà bạn tìm thấy trên điện thoại, và một dải tần số liên lạc gọi là **Channel (Kênh)**.\n\n### 6.2.2 Quá trình kết nối: Scanning và Association\nĐể kết nối vào Wi-Fi, máy tính phải tìm AP:\n- **Passive Scanning (Quét thụ động):** AP liên tục phát sóng các gói tin đèn biển (Beacon Frames) đi khắp nơi. Máy tính lắng nghe, nhặt các gói Beacon này để biết có các mạng nào xung quanh.\n- **Active Scanning (Quét chủ động):** Trái lại, Máy tính sẽ tự phát đi một gói tin Probe Request. Các AP nhận được sẽ phản hồi lại bằng Probe Response.\n\nSau khi chọn một mạng, thiết bị thực hiện Xác thực (Authentication) và Liên kết (Association) với AP.\n\n### 6.2.3 Giao thức Truy cập Kênh: CSMA/CA\nVì vấn đề Terminal ẩn, Wi-Fi KHÔNG dùng CSMA/CD. Khi đang phát sóng vô tuyến, thiết bị không thể vừa phát vừa nghe dò va chạm. Thay vào đó nó dùng **CSMA/CA (Carrier Sense Multiple Access with Collision Avoidance - Tránh va chạm)**.\n- *Nghe trước khi nói:* Nếu kênh rảnh, đợi một chút rồi phát nguyên cả khung dữ liệu (không ngắt giữa chừng).\n- *Lùi lại (Backoff):* Nếu kênh đang bận, thiết bị phải chờ bằng cách chọn số đếm lùi ngẫu nhiên.\n- *ACK ở tầng Link:* Do không thể tự dò va chạm, thiết bị phát sẽ phát xong và chờ đợi. Nếu máy nhận bắt được gói tin an toàn, nó gửi lại một gói ACK ở tầng Link (điều mà Ethernet không làm). Nếu không thấy ACK, máy phát biết là đã rớt gói và sẽ phát lại.\n\n**Cơ chế RTS / CTS để chống Terminal Ẩn:**\nĐể giải quyết bài toán A và C cùng lúc đè tín hiệu vào B. Chuẩn 802.11 cung cấp một cơ chế đặt chỗ tùy chọn:\n1. Máy A gửi trước một gói tin siêu nhỏ: **RTS (Request to Send)** báo xin phát một khung dữ liệu dài X.\n2. Trạm AP B trả lời bằng **CTS (Clear to Send)**. Lệnh CTS này phát rộng ra để cả A và C cùng nghe thấy.\n3. Máy C nghe thấy CTS của B, biết rằng B đang dành sóng cho ai đó truyền khung dài X, C sẽ im lặng.\n4. Máy A nghe thấy CTS, an tâm gửi cục dữ liệu lớn mà không sợ bị C làm nhiễu.\n\n---\n\n## 6.3 Mạng Di động (Cellular Networks) - 4G/5G\n\nMạng di động do các nhà viễn thông cung cấp, bao phủ diện tích rộng hàng chục nghìn kilomet vuông.\nTừ \"Cellular\" xuất phát từ việc khu vực địa lý được chia nhỏ thành các \"Tế bào\" (Cells) hình tổ ong. Mỗi ô tế bào được phục vụ bởi một cột ăng-ten trung tâm gọi là **Base Station (Trạm cơ sở - eNodeB trong 4G LTE)**.\n\n### Cấu trúc 4G LTE\nMạng 4G chia làm hai phần: Mạng truy cập vô tuyến (Radio Access Network) và Mạng lõi (Evolved Packet Core - EPC). Toàn bộ 4G (cả thoại và dữ liệu) đều dựa trên kiến trúc IP (Packet-switched) hoàn toàn.\n\n- **UE (User Equipment):** Điện thoại thông minh, đồng hồ thông minh gắn SIM của bạn.\n- **eNodeB:** Trạm thu phát sóng cơ sở. Quản lý việc cấp phát tài nguyên vô tuyến (băng tần, thời gian) cho các điện thoại trong ô sóng đó.\n- **SGW (Serving Gateway) và PGW (PDN Gateway):** SGW chịu trách nhiệm định tuyến gói tin dữ liệu trong khu vực, PGW là ranh giới gateway kết nối từ mạng di động ra ngoài Internet toàn cầu (làm cả việc NAT địa chỉ IP cho điện thoại).\n- **MME (Mobility Management Entity):** Trung tâm não bộ điều khiển. Đóng vai trò là Control Plane. Nó xác thực người dùng (SIM), và theo dõi vị trí của điện thoại để nếu bạn di chuyển, nó biết để điều phối cuộc gọi.\n- **HSS (Home Subscriber Server):** Cơ sở dữ liệu chứa thông tin các SIM, hồ sơ thanh toán của khách hàng.\n\n---\n\n## 6.4 Quản lý Di động (Mobility Management)\n\nKhi bạn ngồi trên ô tô tốc độ cao, vừa xem YouTube vừa di chuyển từ thành phố này sang thành phố khác. Mạng làm thế nào để gói tin YouTube vẫn tìm được bạn, dù bạn đã rời khỏi cột sóng cũ?\n\n**Vị trí của thiết bị:**\n- **Home Network (Mạng nhà):** Là mạng mà SIM của bạn đăng ký. Ví dụ Viettel Hà Nội.\n- **Home Agent (Đại diện nhà):** Một thực thể ở mạng nhà (thường là router/gateway) lưu giữ thông tin định vị của bạn.\n- **Visited Network / Foreign Network (Mạng khách):** Nếu bạn đi công tác vào TP.HCM, điện thoại kết nối trạm Viettel HCM, đây là mạng khách. Trạm đang phục vụ bạn gọi là Foreign Agent.\n- **Care-of Address (COA):** Khi đến mạng khách, thiết bị của bạn được cấp một địa chỉ IP tạm thời mới gọi là COA.\n\n**Cách định tuyến tới Mobile Node (Định tuyến gián tiếp):**\n1. Một Correspondent (Người gửi) ở xa muốn gửi tin nhắn cho bạn. Nó gửi tới địa chỉ IP CỐ ĐỊNH (Permanent IP) của bạn ở mạng nhà (Hà Nội).\n2. Gói tin đi tới mạng nhà, **Home Agent** ở mạng nhà tóm lấy gói tin này.\n3. Bằng cách nào đó, Home Agent đã biết địa chỉ tạm trú COA hiện tại của bạn ở HCM. Nó nhét gói tin gốc vào một lớp IP thứ 2 (Tunneling) có địa chỉ đích là COA, và ném xuống phương Nam.\n4. Gói tin tới mạng khách, Foreign Agent lột lớp vỏ hầm (decapsulation) và giao gói tin gốc cho điện thoại bạn.\n\n**Handover / Handoff (Chuyển giao sóng):**\nKhi bạn lái xe, điện thoại ra khỏi vùng phủ sóng của trạm eNodeB số 1 và vào vùng trạm eNodeB số 2.\n- Điện thoại của bạn liên tục đo cường độ sóng. Khi nó thấy sóng trạm 2 mạnh hơn trạm 1, nó báo cho trạm 1.\n- Trạm 1 chủ động giao tiếp với trạm 2, dọn đường và bàn giao quản lý (Handover) chiếc điện thoại này sang cho trạm 2 mà không làm rớt mạng. Tốc độ chuyển giao chỉ trong vài chục miligiây.\n\n---\n## TÓM TẮT (KEY TAKEAWAYS)\n- Vô tuyến có suy hao (path loss), nhiễu và dội sóng đa đường. SNR quyết định BER.\n- Bài toán Terminal ẩn là vấn đề hai máy khuất tầm nhìn cùng phát làm hỏng sóng trạm giữa. Giải bằng RTS/CTS.\n- Wi-Fi (802.11) dùng CSMA/CA, phát beacon quét sóng.\n- 4G LTE kiến trúc ALL-IP. Cột sóng gọi là eNodeB, MME điều khiển di động, PGW nối ra Internet.\n- Quản lý di động dùng cấu trúc mạng nhà (Home agent) chuyển hầm (tunneling) gói tin đến mạng khách (COA).\n- Quá trình đi từ trạm sóng này sang trạm khác là Handover.\n"
    },
    {
      "id": "chuong_7",
      "title": "CHƯƠNG 7: AN NINH MẠNG MÁY TÍNH (NETWORK SECURITY)",
      "content": "# CHƯƠNG 7: AN NINH MẠNG MÁY TÍNH (NETWORK SECURITY)\n\nMạng máy tính được xây dựng trên cơ sở các giao thức mở và dễ dàng kết nối. Điều này tạo điều kiện lý tưởng cho kẻ xấu (hackers) rình rập, đánh cắp thông tin, giả mạo và phá hoại hệ thống.\n\n## 7.1 Thế nào là mạng an toàn?\nMột hệ thống giao tiếp an toàn trên không gian mạng phải thỏa mãn các thuộc tính cốt lõi sau:\n1. **Tính bảo mật (Confidentiality):** Chỉ người gửi và người nhận hợp pháp mới có thể ĐỌC VÀ HIỂU được nội dung bản tin. Để đạt được điều này, dữ liệu phải được mã hóa (encrypt) khiến nó trở thành một chuỗi vô nghĩa với kẻ nghe lén.\n2. **Tính toàn vẹn thông điệp (Message Integrity):** Người nhận phải đảm bảo rằng thông điệp họ nhận được CHƯA HỀ BỊ THAY ĐỔI (cố ý hay vô ý) trên đường truyền.\n3. **Xác thực thiết bị cuối (End-point Authentication):** Cả người gửi và người nhận phải chứng minh được DANH TÍNH thật sự của mình cho bên kia biết, tránh trường hợp kẻ gian giả mạo mạo danh (Spoofing).\n4. **Bảo mật vận hành (Operational Security):** Sử dụng các tường lửa (Firewalls) và hệ thống phát hiện xâm nhập (IDS) để bảo vệ mạng nội bộ khỏi các đợt tấn công từ mạng Internet bên ngoài.\n\n---\n\n## 7.2 Mật mã học (Cryptography)\n\nMật mã học là nghệ thuật biến đổi dữ liệu rõ (Plaintext) thành bản mã (Ciphertext) bằng một thuật toán mã hóa và một Chìa khóa (Key). Có hai nhánh chính của mật mã học:\n\n### 7.2.1 Mã hóa Khóa Đối xứng (Symmetric Key Cryptography)\n- **Cơ chế:** Cả người gửi và người nhận đều chia sẻ và sử dụng **CÙNG MỘT KHÓA DUY NHẤT**. Người gửi dùng khóa K để khóa dữ liệu, người nhận dùng khóa K đó để mở dữ liệu.\n- Kỹ thuật:\n  - **Block Cipher (Mã hóa theo khối):** Cắt dữ liệu thành các khối (ví dụ 64 bit, 128 bit) rồi mã hóa độc lập từng khối. Chuẩn mã hóa phổ biến nhất hiện nay là **AES (Advanced Encryption Standard)** dùng khóa 128, 192 hoặc 256 bits. (Trước đây dùng DES nhưng nay đã lỗi thời do dễ bị bẻ khóa bằng brute force).\n- **Ưu điểm:** Tính toán cực kỳ nhanh, tiêu tốn ít tài nguyên phần cứng. Rất thích hợp mã hóa lượng dữ liệu lớn.\n- **Nhược điểm lớn nhất:** Làm sao phân phối khóa bí mật này cho nhau mà không bị kẻ trộm lấy mất trên đường truyền?\n\n### 7.2.2 Mã hóa Khóa Công khai / Bất đối xứng (Public Key Cryptography)\n- **Cơ chế:** Mỗi người sở hữu **MỘT CẶP KHÓA (Pair of Keys)** có liên hệ toán học chặt chẽ với nhau: một Khóa công khai (Public Key - mọi người đều biết) và một Khóa bí mật (Private Key - chỉ người chủ giữ).\n- **Quy tắc vàng:** Dữ liệu mã hóa bằng khóa Công khai thì CHỈ CÓ THỂ ĐƯỢC MỞ bằng Khóa bí mật (và ngược lại).\n- **Ví dụ thuật toán RSA:**\n  - Nếu Alice muốn gửi thư bí mật cho Bob: Alice lấy Public Key của Bob (công khai) để mã hóa thư. Thư mã hóa này giờ không ai đọc được. Nó bay qua mạng. Khi Bob nhận được, Bob lấy Private Key của mình (chỉ mình Bob có) để giải mã.\n- **Ưu điểm:** Giải quyết triệt để bài toán phân phối khóa trên môi trường không an toàn.\n- **Nhược điểm:** Phép toán dùng trong RSA dựa trên việc phân tích các số nguyên tố cực kỳ lớn, tốn tài nguyên máy tính và rất CHẬM (chậm hơn AES hàng ngàn lần).\n- **Ứng dụng thực tế (Session Key):** Người ta kết hợp cả 2! Alice dùng RSA mã hóa một khóa đối xứng nhỏ (Session Key) gửi cho Bob. Sau khi Bob nhận Session Key, hai người cất RSA đi và dùng AES (tốc độ cao) cùng Session Key đó để mã hóa suốt phần còn lại của cuộc hội thoại.\n\n---\n\n## 7.3 Xác thực và Tính toàn vẹn Dữ liệu\n\n### 7.3.1 Hàm Băm Mật mã học (Cryptographic Hash Function)\nHàm băm là thuật toán nhận đầu vào là một thông điệp độ dài tùy ý và tạo ra đầu ra (Hash code/Message Digest) có độ dài CỐ ĐỊNH.\n- Thuộc tính quan trọng: Bất khả nghịch (không thể từ mã băm dịch ngược ra văn bản), và Không đụng độ (cực khó tìm được 2 file khác nhau mà có cùng mã băm).\n- Các thuật toán phổ biến: **MD5** (128 bit - hiện đã không an toàn), **SHA-1** (160 bit), **SHA-256**.\n- **Ứng dụng (MAC - Message Authentication Code):** Để kiểm tra file bị chỉnh sửa trên mạng. Alice và Bob chia sẻ một mật khẩu (s). Alice lấy file ghép với (s), băm ra một mã băm H. Gửi file + H cho Bob. Nếu kẻ tấn công đổi file, H sẽ không khớp nữa.\n\n### 7.3.2 Chữ ký Số (Digital Signatures)\nBản MAC có nhược điểm là 2 bên dùng chung một mật khẩu (s), nếu Alice chối bỏ (Repudiation) rằng \"Tôi không hề tạo ra file đó, là Bob tạo\", thì không ai làm chứng được.\n**Chữ ký số** dùng thuật toán Mã hóa Bất đối xứng (như RSA).\n- Alice lấy file văn bản, Băm nó ra mã băm (Hash digest).\n- Alice dùng **KHÓA BÍ MẬT (PRIVATE KEY)** của cô ấy để mã hóa Hash digest đó. Cục dữ liệu mã hóa đó gọi là Chữ ký số.\n- Alice gửi văn bản kèm chữ ký cho Bob.\n- Bob dùng **KHÓA CÔNG KHAI (PUBLIC KEY)** của Alice để mở chữ ký. Nếu mở được thành công và Hash khớp, chứng tỏ CHẮC CHẮN VÀ DUY NHẤT Alice là người đã ký. Giải quyết được tính xác thực và không thể chối bỏ.\n\n### 7.3.3 Chứng chỉ Số và CA (Certification Authorities)\nMột vấn đề là làm sao Bob biết chắc chắn cái Public Key (mà người ta bảo là của Alice) là đồ thật, chứ không phải đồ giả do Hacker mạo danh?\nMạng lưới sử dụng một bên thứ ba đáng tin cậy gọi là **Trung tâm cấp chứng chỉ (CA - Certification Authority)** (như VeriSign, Let's Encrypt).\n- CA sẽ kiểm tra căn cước công dân thực tế của Alice để xác minh danh tính.\n- CA tạo ra một tờ **Chứng chỉ số (Certificate)** chứa Tên của Alice và Public Key của Alice. Sau đó CA dùng *Private Key của CA* để ký vào Chứng chỉ này.\n- Khi Bob nhận Public Key của Alice kèm chứng chỉ, Bob sẽ dùng Public Key của CA (được cài sẵn trong Windows/MacOS/Browser) để xác minh tờ chứng chỉ.\n\n---\n\n## 7.4 Bảo mật theo từng tầng mạng\n\n### 7.4.1 Mạng riêng ảo - IPsec (Network Layer)\nIPsec cung cấp tính năng bảo mật ở Tầng Mạng (Network Layer). Nghĩa là MỌI giao thức ứng dụng (TCP, UDP, Web, Mail) khi đi qua tầng IP sẽ tự động được bảo mật mã hóa trong suốt.\n- IPsec tạo ra các đường hầm (Virtual Private Networks - VPN) nối trụ sở chính công ty với các văn phòng chi nhánh qua mạng Internet công cộng không an toàn. Dữ liệu bên trong hầm là hoàn toàn bí mật.\n\n### 7.4.2 SSL/TLS (Transport Layer)\nSSL (Secure Sockets Layer) và phiên bản hiện đại hơn là **TLS (Transport Layer Security)** nâng cao bảo mật TCP. Sự kết hợp giữa HTTP và TLS tạo thành **HTTPS**.\nQuá trình bắt tay TLS (TLS Handshake):\n1. Client kết nối tới Server, hai bên thỏa thuận thuật toán mã hóa.\n2. Server gửi Chứng chỉ số (Certificate chứa Public Key) cho Client.\n3. Client xác thực Chứng chỉ. Sau đó Client tự sinh ra một Session Key (Khóa đối xứng), dùng Public Key của Server để mã hóa Session Key rồi gửi lên cho Server.\n4. Từ đó về sau, mọi dữ liệu HTTPS được mã hóa nhanh chóng bằng Session Key đối xứng đó.\n\n### 7.4.3 WPA trong Wi-Fi (Link Layer)\nWEP là chuẩn sơ khai rất dễ bị bẻ khóa. Ngày nay các mạng Wi-Fi bảo mật bởi **WPA2** và **WPA3**. Nó mã hóa từng khung (Frame) vô tuyến ở tầng Liên kết trước khi phát ra sóng, dùng mã hóa AES.\n\n---\n\n## 7.5 Tường lửa (Firewalls) và IDS\n\nTường lửa (Firewall) là một phần cứng/phần mềm đứng ở ranh giới giữa mạng LAN nội bộ và mạng Internet. Có 3 loại:\n1. **Packet Filter (Lọc gói tin truyền thống):** Router sẽ đọc từng gói IP đi qua nó, kiểm tra IP nguồn, IP đích, Cổng nguồn/đích, cờ TCP. Dựa trên bộ quy tắc (ACL - Access Control List) quản trị viên cấu hình để quyết định Cho phép (Allow) hay Bỏ (Drop). Rất nhanh nhưng dễ bị qua mặt.\n2. **Stateful Filter (Lọc có trạng thái):** Tường lửa theo dõi trạng thái các kết nối TCP. Nếu phát hiện một gói tin đến không thuộc một kết nối hợp lệ đang được mở nào cả, nó sẽ cấm.\n3. **Application Gateway (Cổng giao tiếp ứng dụng/Proxy):** Tường lửa hiểu được nội dung của giao thức ứng dụng. Ví dụ, nó có thể chặn mọi gói tin nhưng chỉ cho phép lệnh HTTP GET, hoặc cấm user download file exe, cấm truy cập Facebook. Mức độ bảo vệ sâu nhất nhưng tốn tài nguyên nhất.\n\n**IDS (Intrusion Detection System):** Hệ thống phát hiện xâm nhập. Nó chứa cơ sở dữ liệu hàng ngàn các mẫu (signatures) mã độc, virut, hành vi đáng ngờ. IDS sử dụng DPI (Deep Packet Inspection) để bóc tách và phân tích toàn bộ nội dung của mọi gói tin từ trên xuống dưới, nhằm phát hiện và cảnh báo các cuộc tấn công không thể chặn bằng tường lửa thông thường.\n"
    }
  ]
}